Workbook

Sheet Executive Summary
A1: BD Operations Dashboard — Executive Summary
A2: Source data: BD, Bench, Bench Interview, Market Interview tabs (live)
A3: Auto-updated when source tabs change. Copy fresh source data into the *_Data tabs to refresh.
A5: TOP-LINE BUSINESS KPIs
A6: Total Submissions | B6: Submissions This Month | C6: Onboarded (#) | D6: Submission→Onboard % | E6: Active Pipeline | F6: Bench Strength (RFD) | G6: Total Interviews | H6: Selection Rate
A7: =COUNTA('BD Data'!A2:A165) -> 162 | B7: =COUNTIFS('BD Data'!A2:A165,">="&DATE(YEAR(TODAY()),MONTH(TODAY()),1),'BD Data'!A2:A165,"<="&EOMONTH(TODAY(),0)) -> 154 | C7: =COUNTIF('BD Data'!N2:N165,"Onboarded") -> 4 | D7: =IFERROR(C7/A7,0) -> 0.024691358 | E7: =COUNTIF('BD Data'!N2:N165,"Profile Shared")+COUNTIF('BD Data'!N2:N165,"Screening Scheduled")+COUNTIF('BD Data'!N2:N165,"Interview")+COUNTIF('BD Data'!N2:N165,"Shortlisted")+COUNTIF('BD Data'!N2:N165,"On Hold")+COUNTIF('BD Data'!N2:N165,"Awaiting Feedback")+COUNTIF('BD Data'!N2:N165,"Final Select") -> 56 | F7: =COUNTIF('Bench Data'!D2:D78,"RFD") -> 70 | G7: =COUNTA('Bench Intv Data'!A2:A135)+COUNTA('Market Intv Data'!A2:A36) -> 169 | H7: =IFERROR(SUMPRODUCT(ISNUMBER(SEARCH("Selected",'Bench Intv Data'!I2:I135))*1)/(SUMPRODUCT(ISNUMBER(SEARCH("Selected",'Bench Intv Data'!I2:I135))*1)+SUMPRODUCT(ISNUMBER(SEARCH("Rejected",'Bench Intv Data'!I2:I135))*1)),0) -> 0.65979381
A9: THE STORY IN 3 NUMBERS
A10: Bench yield | D10: Market yield | G10: Profile rejection
A11: Onboarded from Bench source | D11: Onboarded from Market source | G11: Profiles rejected before interview
A12: =COUNTIFS('BD Data'!K2:K165,"Bench",'BD Data'!N2:N165,"Onboarded") -> 4 | B12: of | C12: =COUNTIF('BD Data'!K2:K165,"Bench") -> 88 | D12: =COUNTIFS('BD Data'!K2:K165,"Market",'BD Data'!N2:N165,"Onboarded") -> 0 | E12: of | F12: =COUNTIF('BD Data'!K2:K165,"Market") -> 66 | G12: =COUNTIF('BD Data'!N2:N165,"Profile Rejected") -> 56 | H12: of | I12: =A7 -> 162
A13: =IFERROR(A12/C12,0) -> 0.045454545 | D13: =IFERROR(D12/F12,0) -> 0 | G13: =IFERROR(G12/I12,0) -> 0.34567901
A15: KEY TAKEAWAYS (rules of thumb — verify against current data)
A16: 1. Bench-sourced submissions onboard at ~4.5%; Market submissions at 0.0% — Market sourcing isn't paying off.
A17: 2. 33% of all submissions are Profile Rejected before interview — client-fit screening needs improvement.
A18: 3. REBIT (24 subs, 0 onboarded) and Xebia (13 subs, 0 onboarded) absorb effort without returns.
A19: 4. Kognivera (5 subs, 1 onboarded = 20%) is your most efficient account — invest more there.
A20: 5. Skill gaps: Python (17 demands, 0 bench), Node (11, 0), MERN (6, 0) — hiring would unlock pipeline.
A21: 6. Bench interview selection rate is healthy at 66% — bottleneck is profile acceptance, not interview performance.
A22: 7. Veeru handles 38% of all bench interviews — concentration risk if she's unavailable.
A23: 8. Bushra Sultana has 10 interviews and is still on bench — investigate fit issues.
A25: → See 'Positions' tab for detailed open/closed roles, and 'Targets' tab for engineers (15) & revenue (₹29 Cr) progress.

Sheet Targets
A1: Targets — Engineers (15) and Revenue (₹29 Cr)
A2: Tracks net additions and realized revenue against FY targets. Updates automatically from BD Data and Positions tab.
A4: Engineers Target: | B4: 15 | D4: Revenue Target (₹ Cr): | E4: 29
A6: ENGINEERS — Net additions vs target of 15
A7: Onboarded (YTD) | B7: Target | C7: % of Target | D7: Gap to Close | E7: Waiting to Onboard | F7: Best-case (Onb + Final Sel)
A8: =COUNTIF('BD Data'!N2:N165,"Onboarded") -> 4 | B8: =B4 -> 15 | C8: =IFERROR(A8/B8,0) -> 0.26666667 | D8: =B8-A8 -> 11 | E8: =COUNTIF('BD Data'!N2:N165,"Final Select") -> 6 | F8: =A8+E8 -> 10
A10: Progress: | B10: =REPT("█",A8)&REPT("░",MAX(0,B8-A8)) -> ████░░░░░░░░░░░
A12: REVENUE — Realized vs target of ₹29 Cr
A13: Realized (₹ Cr) | B13: Target (₹ Cr) | C13: % of Target | D13: Gap (₹ Cr) | E13: At Stake — Open (₹ Cr) | F13: Best-case Visible (₹ Cr)
A14: =SUMIFS(Positions!L10:L39,Positions!B10:B39,"CLOSED")/100 -> 0.3 | B14: =E4 -> 29 | C14: =IFERROR(A14/B14,0) -> 0.010344828 | D14: =B14-A14 -> 28.7 | E14: =SUMIFS(Positions!L10:L39,Positions!B10:B39,"OPEN")/100 -> 1.692 | F14: =A14+E14 -> 1.992
A16: Progress: | B16: =REPT("█",ROUND(C14*30,0))&REPT("░",MAX(0,30-ROUND(C14*30,0))) -> ░░░░░░░░░░░░░░░░░░░░░░░░░░░░░░
A18: RUN-RATE ANALYSIS
A19: Tracking start date | E19: 12-Mar-2026
A20: Tracking duration (months) | E20: 2
A21: Engineers — actual run-rate/mo | E21: =A8/2 -> 2
A22: Engineers — required run-rate/mo to hit target | E22: =(B4-A8)/MAX(1,12-2) -> 1.1
A23: Revenue — actual run-rate ₹Cr/mo | E23: =A14/2 -> 0.15
A24: Revenue — required run-rate ₹Cr/mo to hit target | E24: =(E4-A14)/MAX(1,12-2) -> 2.87
A26: VERDICT — Are we on track?
A27: Engineers | B27: =IF(C8>=2/12,"ON TRACK ✓",IF(C8>=2/12*0.7,"BEHIND — needs push","FAR BEHIND — escalate")) -> ON TRACK ✓
A28: Revenue | B28: =IF(C14>=2/12,"ON TRACK ✓",IF(C14>=2/12*0.7,"BEHIND — needs push","FAR BEHIND — escalate")) -> FAR BEHIND — escalate
A30: MONTHLY BREAKDOWN (onboarding by month from BD Data)
A31: Month (Position EnDate) | B31: Onboarded | C31: Revenue (₹ L) | D31: Cumulative Eng | E31: Cumulative Rev (₹ Cr)
A32: Mar-2026 | B32: 3 | C32: 24 | D32: 3 | E32: 0.24
A33: Apr-2026 | B33: 1 | C33: 6 | D33: 4 | E33: 0.3

Sheet Positions
A1: Positions — open & closed roles by client and skill
A2: Each row = unique (Client + Skill + Date) position. OPEN = candidates active in pipeline. CLOSED = someone onboarded. DEAD positions excluded.
A3: Revenue estimate: Budget LPM × Duration months. Where budget missing, default ₹1,00,000/month × 6 months = ₹6L.
A5: POSITION SUMMARY
A6: Open Positions | B6: Closed Positions | C6: Submissions (Open) | D6: Interviews Done (Open) | E6: Avg Days Open | F6: Revenue at Stake (₹L) | G6: Revenue Realized (₹L)
A7: 26 | B7: 4 | C7: 89 | D7: 185 | E7: 14.8 | F7: 169.2 | G7: 30
A9: # | B9: Status | C9: Account | D9: Skill | E9: Location | F9: Work Mode | G9: Position Created | H9: Days Open | I9: Candidates Submitted | J9: Interviews Done | K9: Status Mix | L9: Revenue Estimate (₹L) | M9: Notes
A10: 1 | B10: OPEN | C10: Geekyants | D10: Java | E10: MUM | F10: WFO | G10: 46097 | H10: 40 | I10: 1 | J10: 4 | K10: Final Select(1) | L10: 12 | M10: Est. budget
A11: 2 | B11: OPEN | C11: Zecdata | D11: Java | E11: BLR | F11: WFO | G11: 46105 | H11: 32 | I11: 1 | J11: 5 | K11: Awaiting Feedback(1) | L11: 6 | M11: Est. budget
A12: 3 | B12: OPEN | C12: Prodian | D12: JFSR | E12: Chennai | F12: WFO | G12: 46108 | H12: 29 | I12: 1 | J12: 0 | K12: Profile Shared(1) | L12: 6 | M12: Est. budget
A13: 4 | B13: OPEN | C13: REBIT | D13: Java | E13: BLR | F13: WFO | G13: 46113 | H13: 24 | I13: 18 | J13: 60 | K13: Profile Rejected(6), Profile Shared(6), Final Select(3), Lost / Deferred(2), Interview(1) | L13: 6 | M13: Est. budget
A14: 5 | B14: OPEN | C14: Mangalam | D14: Salesforce | E14: Ahmedabad | F14: Remote | G14: 46114 | H14: 23 | I14: 4 | J14: 0 | K14: Profile Rejected(2), On Hold(1), Lost / Deferred(1) | L14: 6 | M14: Est. budget
A15: 6 | B15: OPEN | C15: Innovation M | D15: Java | E15: Gurgaon | F15: WFO | G15: 46114 | H15: 23 | I15: 5 | J15: 14 | K15: On Hold(4), Profile Rejected(1) | L15: 6 | M15: Est. budget
A16: 7 | B16: OPEN | C16: Xebia | D16: Java | E16: BLR | F16: WFO | G16: 46114 | H16: 23 | I16: 3 | J16: 0 | K16: On Hold(2), Profile Rejected(1) | L16: 6 | M16: Est. budget
A17: 8 | B17: OPEN | C17: Ahana IT | D17: Data Support Engineer | E17: BLR | F17: WFO | G17: 46115 | H17: 22 | I17: 3 | J17: 0 | K17: Lost / Deferred(2), Final Select(1) | L17: 6 | M17: Est. budget
A18: 9 | B18: OPEN | C18: Mangalam | D18: Data Warehouse | E18: Ahmedabad | F18: Remote | G18: 46115 | H18: 22 | I18: 1 | J18: 0 | K18: On Hold(1) | L18: 6 | M18: Est. budget
A19: 10 | B19: OPEN | C19: NPCI | D19: SRE | E19: HYD | F19: WFO | G19: 46119 | H19: 18 | I19: 2 | J19: 0 | K19: Lost / Deferred(1), Screening Scheduled(1) | L19: 6 | M19: Est. budget
A20: 11 | B20: OPEN | C20: Byteridge | D20: .Net | F20: Remote | G20: 46121 | H20: 16 | I20: 3 | J20: 0 | K20: No Show(1), On Hold(1), Profile Rejected(1) | L20: 9
A21: 12 | B21: OPEN | C21: GeekyAnts | D21: Java | E21: BLR | F21: WFO | G21: 46125 | H21: 12 | I21: 4 | J21: 12 | K21: Shortlisted(2), Profile Rejected(2) | L21: 6 | M21: Est. budget
A22: 13 | B22: OPEN | C22: Xebia | D22: Java | E22: MUM | F22: WFO | G22: 46127 | H22: 10 | I22: 4 | J22: 16 | K22: Profile Shared(2), Profile Rejected(1), Final Select(1) | L22: 7.2
A23: 14 | B23: OPEN | C23: REBIT | D23: Java | E23: Mumbai | F23: WFO | G23: 46127 | H23: 10 | I23: 3 | J23: 16 | K23: Profile Shared(1), Profile Rejected(1), Interview(1) | L23: 6 | M23: Est. budget
A24: 15 | B24: OPEN | C24: GeekyAnts | D24: Java | E24: BLR | F24: WFO | G24: 46127 | H24: 10 | I24: 4 | J24: 3 | K24: Profile Rejected(3), Shortlisted(1) | L24: 6 | M24: Est. budget
A25: 16 | B25: OPEN | C25: Xebia | D25: React JS | E25: MUM | F25: WFO | G25: 46128 | H25: 9 | I25: 4 | J25: 7 | K25: Profile Shared(3), Profile Rejected(1) | L25: 7.2
A26: 17 | B26: OPEN | C26: Legistify | D26: MERN | E26: Gurgaon | F26: WFO | G26: 46128 | H26: 9 | I26: 4 | J26: 14 | K26: Profile Shared(4) | L26: 6 | M26: Est. budget
A27: 18 | B27: OPEN | C27: Kognivera | D27: React | E27: BLR | F27: WFO | G27: 46128 | H27: 9 | I27: 4 | J27: 14 | K27: Profile Shared(3), Awaiting Feedback(1) | L27: 6 | M27: Est. budget
A28: 19 | B28: OPEN | C28: 1CHB | D28: Node | E28: CHN | F28: WFO | G28: 46128 | H28: 9 | I28: 4 | J28: 0 | K28: On Hold(2), Lost / Deferred(1), Profile Rejected(1) | L28: 6 | M28: Est. budget
A29: 20 | B29: OPEN | C29: Xebia | D29: Java | E29: MUM | F29: WFO | G29: 46129 | H29: 8 | I29: 2 | J29: 10 | K29: Screening Scheduled(1), Profile Shared(1) | L29: 7.2
A30: 21 | B30: OPEN | C30: XPO | D30: Python | E30: PUNE | F30: WFO | G30: 46129 | H30: 8 | I30: 1 | J30: 0 | K30: Awaiting Feedback(1) | L30: 6 | M30: Est. budget
A31: 22 | B31: OPEN | C31: Utthunga | D31: .NET | E31: BLR | F31: WFO | G31: 46132 | H31: 5 | I31: 3 | J31: 0 | K31: On Hold(1), Profile Rejected(1), Profile Shared(1) | L31: 7.2
A32: 23 | B32: OPEN | C32: Innovation M | D32: Java script | E32: BLR | F32: WFO | G32: 46133 | H32: 4 | I32: 1 | J32: 0 | K32: Profile Shared(1) | L32: 6.6
A33: 24 | B33: OPEN | C33: Coverfox | D33: Android developer | E33: Bangalore | F33: WFO | G33: 46134 | H33: 3 | I33: 4 | J33: 0 | K33: Profile Rejected(2), profile rejected(1), Shortlisted(1) | L33: 4.8
A34: 25 | B34: OPEN | C34: Smallday Tech | D34: AI/ML | E34: PUNE | F34: WFO | G34: 46134 | H34: 3 | I34: 1 | J34: 0 | K34: Profile Shared(1) | L34: 6 | M34: Est. budget
A35: 26 | B35: OPEN | C35: Prodian | D35: JFSR | E35: CHN | F35: WFO | G35: 46134 | H35: 3 | I35: 4 | J35: 10 | K35: Profile Shared(3), Profile Rejected(1) | L35: 6 | M35: Est. budget
A36: 27 | B36: CLOSED | C36: Byteridge | D36: Angular | G36: 46093 | H36: 44 | I36: 1 | J36: 0 | K36: Onboarded(1) | L36: 6
A37: 28 | B37: CLOSED | C37: Kognivera | D37: React | E37: BLR | F37: WFO | G37: 46093 | H37: 44 | I37: 1 | J37: 0 | K37: Onboarded(1) | L37: 6 | M37: Est. budget
A38: 29 | B38: CLOSED | C38: XPO | D38: Python | E38: PUNE | F38: WFO | G38: 46111 | H38: 26 | I38: 3 | J38: 2 | K38: Onboarded(1), Offer Rejected(1), Lost / Deferred(1) | L38: 12 | M38: Est. budget
A39: 30 | B39: CLOSED | C39: Leena.ai | D39: QA | E39: Gurgaon | F39: WFO | G39: 46125 | H39: 12 | I39: 1 | J39: 0 | K39: Onboarded(1) | L39: 6
A42: OPEN POSITIONS BY ACCOUNT (rollup)
A43: Account | B43: Open Positions | C43: Total Subs | D43: Interviews Done | E43: Avg Days Open | F43: Revenue at Stake (₹L)
A44: Xebia | B44: 4 | C44: 13 | D44: 33 | E44: 12.5 | F44: 27.6
A45: Prodian | B45: 2 | C45: 5 | D45: 10 | E45: 16 | F45: 12
A46: REBIT | B46: 2 | C46: 21 | D46: 76 | E46: 17 | F46: 12
A47: Mangalam | B47: 2 | C47: 5 | D47: 0 | E47: 22.5 | F47: 12
A48: Innovation M | B48: 2 | C48: 6 | D48: 14 | E48: 13.5 | F48: 12.6
A49: GeekyAnts | B49: 2 | C49: 8 | D49: 15 | E49: 11 | F49: 12
A50: Geekyants | B50: 1 | C50: 1 | D50: 4 | E50: 40 | F50: 12
A51: Zecdata | B51: 1 | C51: 1 | D51: 5 | E51: 32 | F51: 6
A52: Ahana IT | B52: 1 | C52: 3 | D52: 0 | E52: 22 | F52: 6
A53: NPCI | B53: 1 | C53: 2 | D53: 0 | E53: 18 | F53: 6
A54: Byteridge | B54: 1 | C54: 3 | D54: 0 | E54: 16 | F54: 9
A55: Legistify | B55: 1 | C55: 4 | D55: 14 | E55: 9 | F55: 6
... A61: Smallday Tech | B61: 1 | C61: 1 | D61: 0 | E61: 3 | F61: 6
A64: OPEN POSITIONS BY SKILL (rollup)
A65: Skill | B65: Open Positions | C65: Total Subs | D65: Interviews Done | E65: Avg Days Open | F65: Revenue at Stake (₹L)
A66: Java | B66: 10 | C66: 45 | D66: 140 | E66: 19.2 | F66: 68.4
A67: JFSR | B67: 2 | C67: 5 | D67: 10 | E67: 16 | F67: 12
A68: Salesforce | B68: 1 | C68: 4 | D68: 0 | E68: 23 | F68: 6
A69: Data Support Engineer | B69: 1 | C69: 3 | D69: 0 | E69: 22 | F69: 6
A70: Data Warehouse | B70: 1 | C70: 1 | D70: 0 | E70: 22 | F70: 6
A71: SRE | B71: 1 | C71: 2 | D71: 0 | E71: 18 | F71: 6
A72: .Net | B72: 1 | C72: 3 | D72: 0 | E72: 16 | F72: 9
A73: React JS | B73: 1 | C73: 4 | D73: 7 | E73: 9 | F73: 7.2
A74: MERN | B74: 1 | C74: 4 | D74: 14 | E74: 9 | F74: 6
A75: React | B75: 1 | C75: 4 | D75: 14 | E75: 9 | F75: 6
A76: Node | B76: 1 | C76: 4 | D76: 0 | E76: 9 | F76: 6
A77: Python | B77: 1 | C77: 1 | D77: 0 | E77: 8 | F77: 6
... A81: AI/ML | B81: 1 | C81: 1 | D81: 0 | E81: 3 | F81: 6

Sheet BD Funnel
A1: BD Funnel — submission to onboard conversion
A2: Each row shows count and conversion rate from previous stage.
A4: Stage | B4: Count | C4: % of Total | D4: % of Previous | E4: Notes
A5: Total Submissions | B5: =COUNTA('BD Data'!A2:A165) -> 162 | C5: =IFERROR(B5/$B$5,0) -> 1 | D5: — | E5: All BD entries
A6: Survived Profile Screening | B6: =COUNTA('BD Data'!A2:A165)-COUNTIF('BD Data'!N2:N165,"Profile Rejected")-COUNTIF('BD Data'!N2:N165,"Lost / Deferred")-COUNTIF('BD Data'!N2:N165,"Requirement Received")-COUNTIF('BD Data'!N2:N165,"Requirement Shared") -> 67 | C6: =IFERROR(B6/$B$5,0) -> 0.41358025 | D6: =IFERROR(B6/B5,0) -> 0.41358025 | E6: Got past initial profile rejection
A7: Reached Interview Stage | B7: =COUNTIF('BD Data'!N2:N165,"Profile Shared")+COUNTIF('BD Data'!N2:N165,"Awaiting Feedback")+COUNTIF('BD Data'!N2:N165,"Interview")+COUNTIF('BD Data'!N2:N165,"Screening Scheduled")+COUNTIF('BD Data'!N2:N165,"Shortlisted")+COUNTIF('BD Data'!N2:N165,"On Hold")+COUNTIF('BD Data'!N2:N165,"No Show")+COUNTIF('BD Data'!N2:N165,"Final Select")+COUNTIF('BD Data'!N2:N165,"Offer Rejected")+COUNTIF('BD Data'!N2:N165,"Onboarded") -> 65 | C7: =IFERROR(B7/$B$5,0) -> 0.40123457 | D7: =IFERROR(B7/B6,0) -> 0.97014925 | E7: Active in interview process or beyond
A8: Cleared Multiple Rounds | B8: =COUNTIF('BD Data'!N2:N165,"Shortlisted")+COUNTIF('BD Data'!N2:N165,"Final Select")+COUNTIF('BD Data'!N2:N165,"Offer Rejected")+COUNTIF('BD Data'!N2:N165,"Onboarded") -> 15 | C8: =IFERROR(B8/$B$5,0) -> 0.092592593 | D8: =IFERROR(B8/B7,0) -> 0.23076923 | E8: Shortlisted or beyond
A9: Received Offer | B9: =COUNTIF('BD Data'!N2:N165,"Final Select")+COUNTIF('BD Data'!N2:N165,"Offer Rejected")+COUNTIF('BD Data'!N2:N165,"Onboarded") -> 11 | C9: =IFERROR(B9/$B$5,0) -> 0.067901235 | D9: =IFERROR(B9/B8,0) -> 0.73333333 | E9: Offer made
A10: Accepted Offer | B10: =COUNTIF('BD Data'!N2:N165,"Onboarded")+COUNTIF('BD Data'!N2:N165,"Final Select") -> 10 | C10: =IFERROR(B10/$B$5,0) -> 0.061728395 | D10: =IFERROR(B10/B9,0) -> 0.90909091 | E10: Final Select + Onboarded (excludes Offer Rejected)
A11: Onboarded (Revenue) | B11: =COUNTIF('BD Data'!N2:N165,"Onboarded") -> 4 | C11: =IFERROR(B11/$B$5,0) -> 0.024691358 | D11: =IFERROR(B11/B10,0) -> 0.4 | E11: Generating revenue
A14: VISUAL FUNNEL
A15: Total Submissions | B15: =B5 -> 162 | C15: =REPT("█",B5) -> ██████████████████████████████████████████████████████████████████████████████████████████████████████████████████████████████████████████████████████████████████
A16: Survived Profile Screening | B16: =B6 -> 67 | C16: =REPT("█",B6) -> ███████████████████████████████████████████████████████████████████
A17: Reached Interview Stage | B17: =B7 -> 65 | C17: =REPT("█",B7) -> █████████████████████████████████████████████████████████████████
A18: Cleared Multiple Rounds | B18: =B8 -> 15 | C18: =REPT("█",B8) -> ███████████████
A19: Received Offer | B19: =B9 -> 11 | C19: =REPT("█",B9) -> ███████████
A20: Accepted Offer | B20: =B10 -> 10 | C20: =REPT("█",B10) -> ██████████
A21: Onboarded (Revenue) | B21: =B11 -> 4 | C21: =REPT("█",B11) -> ████

Sheet Account Scorecard
A1: Account Scorecard — per-client ROI
A2: Sorted manually by total submissions. Add accounts in column A as needed.
A4: Account | B4: Submissions | C4: Profile Rejected | D4: Active Pipeline | E4: Final Select | F4: Onboarded | G4: Reject Rate | H4: Onboard Rate
A5: REBIT | B5: =COUNTIF('BD Data'!B2:B165,A5) -> 24 | C5: =COUNTIFS('BD Data'!B2:B165,A5,'BD Data'!N2:N165,"Profile Rejected") -> 8 | D5: =COUNTIFS('BD Data'!B2:B165,A5,'BD Data'!N2:N165,"Profile Shared")+COUNTIFS('BD Data'!B2:B165,A5,'BD Data'!N2:N165,"Awaiting Feedback")+COUNTIFS('BD Data'!B2:B165,A5,'BD Data'!N2:N165,"Shortlisted")+COUNTIFS('BD Data'!B2:B165,A5,'BD Data'!N2:N165,"On Hold")+COUNTIFS('BD Data'!B2:B165,A5,'BD Data'!N2:N165,"Interview") -> 9 | E5: =COUNTIFS('BD Data'!B2:B165,A5,'BD Data'!N2:N165,"Final Select") -> 3 | F5: =COUNTIFS('BD Data'!B2:B165,A5,'BD Data'!N2:N165,"Onboarded") -> 0 | G5: =IFERROR(C5/B5,0) -> 0.33333333 | H5: =IFERROR(F5/B5,0) -> 0
A6: Xebia | B6: =COUNTIF('BD Data'!B2:B165,A6) -> 13 | C6: =COUNTIFS('BD Data'!B2:B165,A6,'BD Data'!N2:N165,"Profile Rejected") -> 3 | D6: =COUNTIFS('BD Data'!B2:B165,A6,'BD Data'!N2:N165,"Profile Shared")+COUNTIFS('BD Data'!B2:B165,A6,'BD Data'!N2:N165,"Awaiting Feedback")+COUNTIFS('BD Data'!B2:B165,A6,'BD Data'!N2:N165,"Shortlisted")+COUNTIFS('BD Data'!B2:B165,A6,'BD Data'!N2:N165,"On Hold")+COUNTIFS('BD Data'!B2:B165,A6,'BD Data'!N2:N165,"Interview") -> 8 | E6: =COUNTIFS('BD Data'!B2:B165,A6,'BD Data'!N2:N165,"Final Select") -> 1 | F6: =COUNTIFS('BD Data'!B2:B165,A6,'BD Data'!N2:N165,"Onboarded") -> 0 | G6: =IFERROR(C6/B6,0) -> 0.23076923 | H6: =IFERROR(F6/B6,0) -> 0
A7: 1CHB | B7: =COUNTIF('BD Data'!B2:B165,A7) -> 13 | C7: =COUNTIFS('BD Data'!B2:B165,A7,'BD Data'!N2:N165,"Profile Rejected") -> 7 | D7: =COUNTIFS('BD Data'!B2:B165,A7,'BD Data'!N2:N165,"Profile Shared")+COUNTIFS('BD Data'!B2:B165,A7,'BD Data'!N2:N165,"Awaiting Feedback")+COUNTIFS('BD Data'!B2:B165,A7,'BD Data'!N2:N165,"Shortlisted")+COUNTIFS('BD Data'!B2:B165,A7,'BD Data'!N2:N165,"On Hold")+COUNTIFS('BD Data'!B2:B165,A7,'BD Data'!N2:N165,"Interview") -> 2 | E7: =COUNTIFS('BD Data'!B2:B165,A7,'BD Data'!N2:N165,"Final Select") -> 0 | F7: =COUNTIFS('BD Data'!B2:B165,A7,'BD Data'!N2:N165,"Onboarded") -> 0 | G7: =IFERROR(C7/B7,0) -> 0.53846154 | H7: =IFERROR(F7/B7,0) -> 0
A8: Byteridge | B8: =COUNTIF('BD Data'!B2:B165,A8) -> 10 | C8: =COUNTIFS('BD Data'!B2:B165,A8,'BD Data'!N2:N165,"Profile Rejected") -> 5 | D8: =COUNTIFS('BD Data'!B2:B165,A8,'BD Data'!N2:N165,"Profile Shared")+COUNTIFS('BD Data'!B2:B165,A8,'BD Data'!N2:N165,"Awaiting Feedback")+COUNTIFS('BD Data'!B2:B165,A8,'BD Data'!N2:N165,"Shortlisted")+COUNTIFS('BD Data'!B2:B165,A8,'BD Data'!N2:N165,"On Hold")+COUNTIFS('BD Data'!B2:B165,A8,'BD Data'!N2:N165,"Interview") -> 1 | E8: =COUNTIFS('BD Data'!B2:B165,A8,'BD Data'!N2:N165,"Final Select") -> 0 | F8: =COUNTIFS('BD Data'!B2:B165,A8,'BD Data'!N2:N165,"Onboarded") -> 1 | G8: =IFERROR(C8/B8,0) -> 0.5 | H8: =IFERROR(F8/B8,0) -> 0.1
A9: XPO | B9: =COUNTIF('BD Data'!B2:B165,A9) -> 12 | C9: =COUNTIFS('BD Data'!B2:B165,A9,'BD Data'!N2:N165,"Profile Rejected") -> 6 | D9: =COUNTIFS('BD Data'!B2:B165,A9,'BD Data'!N2:N165,"Profile Shared")+COUNTIFS('BD Data'!B2:B165,A9,'BD Data'!N2:N165,"Awaiting Feedback")+COUNTIFS('BD Data'!B2:B165,A9,'BD Data'!N2:N165,"Shortlisted")+COUNTIFS('BD Data'!B2:B165,A9,'BD Data'!N2:N165,"On Hold")+COUNTIFS('BD Data'!B2:B165,A9,'BD Data'!N2:N165,"Interview") -> 1 | E9: =COUNTIFS('BD Data'!B2:B165,A9,'BD Data'!N2:N165,"Final Select") -> 0 | F9: =COUNTIFS('BD Data'!B2:B165,A9,'BD Data'!N2:N165,"Onboarded") -> 1 | G9: =IFERROR(C9/B9,0) -> 0.5 | H9: =IFERROR(F9/B9,0) -> 0.083333333
A10: Neosoft | B10: =COUNTIF('BD Data'!B2:B165,A10) -> 8 | C10: =COUNTIFS('BD Data'!B2:B165,A10,'BD Data'!N2:N165,"Profile Rejected") -> 2 | D10: =COUNTIFS('BD Data'!B2:B165,A10,'BD Data'!N2:N165,"Profile Shared")+COUNTIFS('BD Data'!B2:B165,A10,'BD Data'!N2:N165,"Awaiting Feedback")+COUNTIFS('BD Data'!B2:B165,A10,'BD Data'!N2:N165,"Shortlisted")+COUNTIFS('BD Data'!B2:B165,A10,'BD Data'!N2:N165,"On Hold")+COUNTIFS('BD Data'!B2:B165,A10,'BD Data'!N2:N165,"Interview") -> 0 | E10: =COUNTIFS('BD Data'!B2:B165,A10,'BD Data'!N2:N165,"Final Select") -> 0 | F10: =COUNTIFS('BD Data'!B2:B165,A10,'BD Data'!N2:N165,"Onboarded") -> 0 | G10: =IFERROR(C10/B10,0) -> 0.25 | H10: =IFERROR(F10/B10,0) -> 0
A11: GeekyAnts | B11: =COUNTIF('BD Data'!B2:B165,A11) -> 9 | C11: =COUNTIFS('BD Data'!B2:B165,A11,'BD Data'!N2:N165,"Profile Rejected") -> 5 | D11: =COUNTIFS('BD Data'!B2:B165,A11,'BD Data'!N2:N165,"Profile Shared")+COUNTIFS('BD Data'!B2:B165,A11,'BD Data'!N2:N165,"Awaiting Feedback")+COUNTIFS('BD Data'!B2:B165,A11,'BD Data'!N2:N165,"Shortlisted")+COUNTIFS('BD Data'!B2:B165,A11,'BD Data'!N2:N165,"On Hold")+COUNTIFS('BD Data'!B2:B165,A11,'BD Data'!N2:N165,"Interview") -> 3 | E11: =COUNTIFS('BD Data'!B2:B165,A11,'BD Data'!N2:N165,"Final Select") -> 1 | F11: =COUNTIFS('BD Data'!B2:B165,A11,'BD Data'!N2:N165,"Onboarded") -> 0 | G11: =IFERROR(C11/B11,0) -> 0.55555556 | H11: =IFERROR(F11/B11,0) -> 0
A12: Zecdata | B12: =COUNTIF('BD Data'!B2:B165,A12) -> 7 | C12: =COUNTIFS('BD Data'!B2:B165,A12,'BD Data'!N2:N165,"Profile Rejected") -> 4 | D12: =COUNTIFS('BD Data'!B2:B165,A12,'BD Data'!N2:N165,"Profile Shared")+COUNTIFS('BD Data'!B2:B165,A12,'BD Data'!N2:N165,"Awaiting Feedback")+COUNTIFS('BD Data'!B2:B165,A12,'BD Data'!N2:N165,"Shortlisted")+COUNTIFS('BD Data'!B2:B165,A12,'BD Data'!N2:N165,"On Hold")+COUNTIFS('BD Data'!B2:B165,A12,'BD Data'!N2:N165,"Interview") -> 1 | E12: =COUNTIFS('BD Data'!B2:B165,A12,'BD Data'!N2:N165,"Final Select") -> 0 | F12: =COUNTIFS('BD Data'!B2:B165,A12,'BD Data'!N2:N165,"Onboarded") -> 0 | G12: =IFERROR(C12/B12,0) -> 0.57142857 | H12: =IFERROR(F12/B12,0) -> 0
A13: Ahana IT | B13: =COUNTIF('BD Data'!B2:B165,A13) -> 7 | C13: =COUNTIFS('BD Data'!B2:B165,A13,'BD Data'!N2:N165,"Profile Rejected") -> 2 | D13: =COUNTIFS('BD Data'!B2:B165,A13,'BD Data'!N2:N165,"Profile Shared")+COUNTIFS('BD Data'!B2:B165,A13,'BD Data'!N2:N165,"Awaiting Feedback")+COUNTIFS('BD Data'!B2:B165,A13,'BD Data'!N2:N165,"Shortlisted")+COUNTIFS('BD Data'!B2:B165,A13,'BD Data'!N2:N165,"On Hold")+COUNTIFS('BD Data'!B2:B165,A13,'BD Data'!N2:N165,"Interview") -> 0 | E13: =COUNTIFS('BD Data'!B2:B165,A13,'BD Data'!N2:N165,"Final Select") -> 1 | F13: =COUNTIFS('BD Data'!B2:B165,A13,'BD Data'!N2:N165,"Onboarded") -> 0 | G13: =IFERROR(C13/B13,0) -> 0.28571429 | H13: =IFERROR(F13/B13,0) -> 0
A14: Innovation M | B14: =COUNTIF('BD Data'!B2:B165,A14) -> 6 | C14: =COUNTIFS('BD Data'!B2:B165,A14,'BD Data'!N2:N165,"Profile Rejected") -> 1 | D14: =COUNTIFS('BD Data'!B2:B165,A14,'BD Data'!N2:N165,"Profile Shared")+COUNTIFS('BD Data'!B2:B165,A14,'BD Data'!N2:N165,"Awaiting Feedback")+COUNTIFS('BD Data'!B2:B165,A14,'BD Data'!N2:N165,"Shortlisted")+COUNTIFS('BD Data'!B2:B165,A14,'BD Data'!N2:N165,"On Hold")+COUNTIFS('BD Data'!B2:B165,A14,'BD Data'!N2:N165,"Interview") -> 5 | E14: =COUNTIFS('BD Data'!B2:B165,A14,'BD Data'!N2:N165,"Final Select") -> 0 | F14: =COUNTIFS('BD Data'!B2:B165,A14,'BD Data'!N2:N165,"Onboarded") -> 0 | G14: =IFERROR(C14/B14,0) -> 0.16666667 | H14: =IFERROR(F14/B14,0) -> 0
A15: Kognivera | B15: =COUNTIF('BD Data'!B2:B165,A15) -> 5 | C15: =COUNTIFS('BD Data'!B2:B165,A15,'BD Data'!N2:N165,"Profile Rejected") -> 0 | D15: =COUNTIFS('BD Data'!B2:B165,A15,'BD Data'!N2:N165,"Profile Shared")+COUNTIFS('BD Data'!B2:B165,A15,'BD Data'!N2:N165,"Awaiting Feedback")+COUNTIFS('BD Data'!B2:B165,A15,'BD Data'!N2:N165,"Shortlisted")+COUNTIFS('BD Data'!B2:B165,A15,'BD Data'!N2:N165,"On Hold")+COUNTIFS('BD Data'!B2:B165,A15,'BD Data'!N2:N165,"Interview") -> 4 | E15: =COUNTIFS('BD Data'!B2:B165,A15,'BD Data'!N2:N165,"Final Select") -> 0 | F15: =COUNTIFS('BD Data'!B2:B165,A15,'BD Data'!N2:N165,"Onboarded") -> 1 | G15: =IFERROR(C15/B15,0) -> 0 | H15: =IFERROR(F15/B15,0) -> 0.2
A16: Prodian | B16: =COUNTIF('BD Data'!B2:B165,A16) -> 5 | C16: =COUNTIFS('BD Data'!B2:B165,A16,'BD Data'!N2:N165,"Profile Rejected") -> 1 | D16: =COUNTIFS('BD Data'!B2:B165,A16,'BD Data'!N2:N165,"Profile Shared")+COUNTIFS('BD Data'!B2:B165,A16,'BD Data'!N2:N165,"Awaiting Feedback")+COUNTIFS('BD Data'!B2:B165,A16,'BD Data'!N2:N165,"Shortlisted")+COUNTIFS('BD Data'!B2:B165,A16,'BD Data'!N2:N165,"On Hold")+COUNTIFS('BD Data'!B2:B165,A16,'BD Data'!N2:N165,"Interview") -> 4 | E16: =COUNTIFS('BD Data'!B2:B165,A16,'BD Data'!N2:N165,"Final Select") -> 0 | F16: =COUNTIFS('BD Data'!B2:B165,A16,'BD Data'!N2:N165,"Onboarded") -> 0 | G16: =IFERROR(C16/B16,0) -> 0.2 | H16: =IFERROR(F16/B16,0) -> 0
A17: Mangalam | B17: =COUNTIF('BD Data'!B2:B165,A17) -> 5 | C17: =COUNTIFS('BD Data'!B2:B165,A17,'BD Data'!N2:N165,"Profile Rejected") -> 2 | D17: =COUNTIFS('BD Data'!B2:B165,A17,'BD Data'!N2:N165,"Profile Shared")+COUNTIFS('BD Data'!B2:B165,A17,'BD Data'!N2:N165,"Awaiting Feedback")+COUNTIFS('BD Data'!B2:B165,A17,'BD Data'!N2:N165,"Shortlisted")+COUNTIFS('BD Data'!B2:B165,A17,'BD Data'!N2:N165,"On Hold")+COUNTIFS('BD Data'!B2:B165,A17,'BD Data'!N2:N165,"Interview") -> 2 | E17: =COUNTIFS('BD Data'!B2:B165,A17,'BD Data'!N2:N165,"Final Select") -> 0 | F17: =COUNTIFS('BD Data'!B2:B165,A17,'BD Data'!N2:N165,"Onboarded") -> 0 | G17: =IFERROR(C17/B17,0) -> 0.4 | H17: =IFERROR(F17/B17,0) -> 0
A18: Tarams | B18: =COUNTIF('BD Data'!B2:B165,A18) -> 5 | C18: =COUNTIFS('BD Data'!B2:B165,A18,'BD Data'!N2:N165,"Profile Rejected") -> 0 | D18: =COUNTIFS('BD Data'!B2:B165,A18,'BD Data'!N2:N165,"Profile Shared")+COUNTIFS('BD Data'!B2:B165,A18,'BD Data'!N2:N165,"Awaiting Feedback")+COUNTIFS('BD Data'!B2:B165,A18,'BD Data'!N2:N165,"Shortlisted")+COUNTIFS('BD Data'!B2:B165,A18,'BD Data'!N2:N165,"On Hold")+COUNTIFS('BD Data'!B2:B165,A18,'BD Data'!N2:N165,"Interview") -> 0 | E18: =COUNTIFS('BD Data'!B2:B165,A18,'BD Data'!N2:N165,"Final Select") -> 0 | F18: =COUNTIFS('BD Data'!B2:B165,A18,'BD Data'!N2:N165,"Onboarded") -> 0 | G18: =IFERROR(C18/B18,0) -> 0 | H18: =IFERROR(F18/B18,0) -> 0
A19: Deservely | B19: =COUNTIF('BD Data'!B2:B165,A19) -> 4 | C19: =COUNTIFS('BD Data'!B2:B165,A19,'BD Data'!N2:N165,"Profile Rejected") -> 1 | D19: =COUNTIFS('BD Data'!B2:B165,A19,'BD Data'!N2:N165,"Profile Shared")+COUNTIFS('BD Data'!B2:B165,A19,'BD Data'!N2:N165,"Awaiting Feedback")+COUNTIFS('BD Data'!B2:B165,A19,'BD Data'!N2:N165,"Shortlisted")+COUNTIFS('BD Data'!B2:B165,A19,'BD Data'!N2:N165,"On Hold")+COUNTIFS('BD Data'!B2:B165,A19,'BD Data'!N2:N165,"Interview") -> 0 | E19: =COUNTIFS('BD Data'!B2:B165,A19,'BD Data'!N2:N165,"Final Select") -> 0 | F19: =COUNTIFS('BD Data'!B2:B165,A19,'BD Data'!N2:N165,"Onboarded") -> 0 | G19: =IFERROR(C19/B19,0) -> 0.25 | H19: =IFERROR(F19/B19,0) -> 0
A20: Legistify | B20: =COUNTIF('BD Data'!B2:B165,A20) -> 4 | C20: =COUNTIFS('BD Data'!B2:B165,A20,'BD Data'!N2:N165,"Profile Rejected") -> 0 | D20: =COUNTIFS('BD Data'!B2:B165,A20,'BD Data'!N2:N165,"Profile Shared")+COUNTIFS('BD Data'!B2:B165,A20,'BD Data'!N2:N165,"Awaiting Feedback")+COUNTIFS('BD Data'!B2:B165,A20,'BD Data'!N2:N165,"Shortlisted")+COUNTIFS('BD Data'!B2:B165,A20,'BD Data'!N2:N165,"On Hold")+COUNTIFS('BD Data'!B2:B165,A20,'BD Data'!N2:N165,"Interview") -> 4 | E20: =COUNTIFS('BD Data'!B2:B165,A20,'BD Data'!N2:N165,"Final Select") -> 0 | F20: =COUNTIFS('BD Data'!B2:B165,A20,'BD Data'!N2:N165,"Onboarded") -> 0 | G20: =IFERROR(C20/B20,0) -> 0 | H20: =IFERROR(F20/B20,0) -> 0
A21: Coverfox | B21: =COUNTIF('BD Data'!B2:B165,A21) -> 4 | C21: =COUNTIFS('BD Data'!B2:B165,A21,'BD Data'!N2:N165,"Profile Rejected") -> 3 | D21: =COUNTIFS('BD Data'!B2:B165,A21,'BD Data'!N2:N165,"Profile Shared")+COUNTIFS('BD Data'!B2:B165,A21,'BD Data'!N2:N165,"Awaiting Feedback")+COUNTIFS('BD Data'!B2:B165,A21,'BD Data'!N2:N165,"Shortlisted")+COUNTIFS('BD Data'!B2:B165,A21,'BD Data'!N2:N165,"On Hold")+COUNTIFS('BD Data'!B2:B165,A21,'BD Data'!N2:N165,"Interview") -> 1 | E21: =COUNTIFS('BD Data'!B2:B165,A21,'BD Data'!N2:N165,"Final Select") -> 0 | F21: =COUNTIFS('BD Data'!B2:B165,A21,'BD Data'!N2:N165,"Onboarded") -> 0 | G21: =IFERROR(C21/B21,0) -> 0.75 | H21: =IFERROR(F21/B21,0) -> 0
A22: Bravura Solutions | B22: =COUNTIF('BD Data'!B2:B165,A22) -> 3 | C22: =COUNTIFS('BD Data'!B2:B165,A22,'BD Data'!N2:N165,"Profile Rejected") -> 0 | D22: =COUNTIFS('BD Data'!B2:B165,A22,'BD Data'!N2:N165,"Profile Shared")+COUNTIFS('BD Data'!B2:B165,A22,'BD Data'!N2:N165,"Awaiting Feedback")+COUNTIFS('BD Data'!B2:B165,A22,'BD Data'!N2:N165,"Shortlisted")+COUNTIFS('BD Data'!B2:B165,A22,'BD Data'!N2:N165,"On Hold")+COUNTIFS('BD Data'!B2:B165,A22,'BD Data'!N2:N165,"Interview") -> 0 | E22: =COUNTIFS('BD Data'!B2:B165,A22,'BD Data'!N2:N165,"Final Select") -> 0 | F22: =COUNTIFS('BD Data'!B2:B165,A22,'BD Data'!N2:N165,"Onboarded") -> 0 | G22: =IFERROR(C22/B22,0) -> 0 | H22: =IFERROR(F22/B22,0) -> 0
A23: Utthunga | B23: =COUNTIF('BD Data'!B2:B165,A23) -> 3 | C23: =COUNTIFS('BD Data'!B2:B165,A23,'BD Data'!N2:N165,"Profile Rejected") -> 1 | D23: =COUNTIFS('BD Data'!B2:B165,A23,'BD Data'!N2:N165,"Profile Shared")+COUNTIFS('BD Data'!B2:B165,A23,'BD Data'!N2:N165,"Awaiting Feedback")+COUNTIFS('BD Data'!B2:B165,A23,'BD Data'!N2:N165,"Shortlisted")+COUNTIFS('BD Data'!B2:B165,A23,'BD Data'!N2:N165,"On Hold")+COUNTIFS('BD Data'!B2:B165,A23,'BD Data'!N2:N165,"Interview") -> 2 | E23: =COUNTIFS('BD Data'!B2:B165,A23,'BD Data'!N2:N165,"Final Select") -> 0 | F23: =COUNTIFS('BD Data'!B2:B165,A23,'BD Data'!N2:N165,"Onboarded") -> 0 | G23: =IFERROR(C23/B23,0) -> 0.33333333 | H23: =IFERROR(F23/B23,0) -> 0
A24: Medimpact | B24: =COUNTIF('BD Data'!B2:B165,A24) -> 0 | C24: =COUNTIFS('BD Data'!B2:B165,A24,'BD Data'!N2:N165,"Profile Rejected") -> 0 | D24: =COUNTIFS('BD Data'!B2:B165,A24,'BD Data'!N2:N165,"Profile Shared")+COUNTIFS('BD Data'!B2:B165,A24,'BD Data'!N2:N165,"Awaiting Feedback")+COUNTIFS('BD Data'!B2:B165,A24,'BD Data'!N2:N165,"Shortlisted")+COUNTIFS('BD Data'!B2:B165,A24,'BD Data'!N2:N165,"On Hold")+COUNTIFS('BD Data'!B2:B165,A24,'BD Data'!N2:N165,"Interview") -> 0 | E24: =COUNTIFS('BD Data'!B2:B165,A24,'BD Data'!N2:N165,"Final Select") -> 0 | F24: =COUNTIFS('BD Data'!B2:B165,A24,'BD Data'!N2:N165,"Onboarded") -> 0 | G24: =IFERROR(C24/B24,0) -> 0 | H24: =IFERROR(F24/B24,0) -> 0
A25: TOTAL | B25: =SUM(B5:B24) -> 147 | C25: =SUM(C5:C24) -> 51 | D25: =SUM(D5:D24) -> 47 | E25: =SUM(E5:E24) -> 6 | F25: =SUM(F5:F24) -> 3 | G25: =IFERROR(C25/B25,0) -> 0.34693878 | H25: =IFERROR(F25/B25,0) -> 0.020408163

Sheet Skill Gap
A1: Skill Gap — bench supply vs market demand
A2: Demand = client requirements in BD Data. Supply = RFD bench resources.
A4: Skill | B4: Demand (Requirements) | C4: Bench Supply (RFD) | D4: Gap | E4: Onboarded | F4: Submissions | G4: Conversion % | H4: Action
A5: Java | B5: =SUMPRODUCT(ISNUMBER(SEARCH("Java",'BD Data'!C2:C165))*1) -> 62 | C5: =SUMPRODUCT(ISNUMBER(SEARCH("Java",'Bench Data'!L2:L78))*('Bench Data'!D2:D78="RFD")) -> 42 | D5: =C5-B5 -> -20 | E5: =SUMPRODUCT(ISNUMBER(SEARCH("Java",'BD Data'!C2:C165))*('BD Data'!N2:N165="Onboarded")) -> 0 | F5: =B5 -> 62 | G5: =IFERROR(E5/F5,0) -> 0 | H5: Aligned
A6: JFSR | B6: =SUMPRODUCT(ISNUMBER(SEARCH("JFSR",'BD Data'!C2:C165))*1) -> 9 | C6: =SUMPRODUCT(ISNUMBER(SEARCH("JFSR",'Bench Data'!L2:L78))*('Bench Data'!D2:D78="RFD")) -> 10 | D6: =C6-B6 -> 1 | E6: =SUMPRODUCT(ISNUMBER(SEARCH("JFSR",'BD Data'!C2:C165))*('BD Data'!N2:N165="Onboarded")) -> 0 | F6: =B6 -> 9 | G6: =IFERROR(E6/F6,0) -> 0 | H6: Aligned
A7: React | B7: =SUMPRODUCT(ISNUMBER(SEARCH("React",'BD Data'!C2:C165))*1) -> 19 | C7: =SUMPRODUCT(ISNUMBER(SEARCH("React",'Bench Data'!L2:L78))*('Bench Data'!D2:D78="RFD")) -> 18 | D7: =C7-B7 -> -1 | E7: =SUMPRODUCT(ISNUMBER(SEARCH("React",'BD Data'!C2:C165))*('BD Data'!N2:N165="Onboarded")) -> 1 | F7: =B7 -> 19 | G7: =IFERROR(E7/F7,0) -> 0.052631579 | H7: Aligned
A8: Python | B8: =SUMPRODUCT(ISNUMBER(SEARCH("Python",'BD Data'!C2:C165))*1) -> 17 | C8: =SUMPRODUCT(ISNUMBER(SEARCH("Python",'Bench Data'!L2:L78))*('Bench Data'!D2:D78="RFD")) -> 0 | D8: =C8-B8 -> -17 | E8: =SUMPRODUCT(ISNUMBER(SEARCH("Python",'BD Data'!C2:C165))*('BD Data'!N2:N165="Onboarded")) -> 1 | F8: =B8 -> 17 | G8: =IFERROR(E8/F8,0) -> 0.058823529 | H8: HIRE — high demand, no bench
A9: Node | B9: =SUMPRODUCT(ISNUMBER(SEARCH("Node",'BD Data'!C2:C165))*1) -> 12 | C9: =SUMPRODUCT(ISNUMBER(SEARCH("Node",'Bench Data'!L2:L78))*('Bench Data'!D2:D78="RFD")) -> 0 | D9: =C9-B9 -> -12 | E9: =SUMPRODUCT(ISNUMBER(SEARCH("Node",'BD Data'!C2:C165))*('BD Data'!N2:N165="Onboarded")) -> 0 | F9: =B9 -> 12 | G9: =IFERROR(E9/F9,0) -> 0 | H9: HIRE — high demand, no bench
A10: MERN | B10: =SUMPRODUCT(ISNUMBER(SEARCH("MERN",'BD Data'!C2:C165))*1) -> 6 | C10: =SUMPRODUCT(ISNUMBER(SEARCH("MERN",'Bench Data'!L2:L78))*('Bench Data'!D2:D78="RFD")) -> 0 | D10: =C10-B10 -> -6 | E10: =SUMPRODUCT(ISNUMBER(SEARCH("MERN",'BD Data'!C2:C165))*('BD Data'!N2:N165="Onboarded")) -> 0 | F10: =B10 -> 6 | G10: =IFERROR(E10/F10,0) -> 0 | H10: HIRE — high demand, no bench
A11: GoLang | B11: =SUMPRODUCT(ISNUMBER(SEARCH("GoLang",'BD Data'!C2:C165))*1) -> 8 | C11: =SUMPRODUCT(ISNUMBER(SEARCH("GoLang",'Bench Data'!L2:L78))*('Bench Data'!D2:D78="RFD")) -> 0 | D11: =C11-B11 -> -8 | E11: =SUMPRODUCT(ISNUMBER(SEARCH("GoLang",'BD Data'!C2:C165))*('BD Data'!N2:N165="Onboarded")) -> 0 | F11: =B11 -> 8 | G11: =IFERROR(E11/F11,0) -> 0 | H11: Watch
A12: .NET | B12: =SUMPRODUCT(ISNUMBER(SEARCH(".Net",'BD Data'!C2:C165))*1) -> 8 | C12: =SUMPRODUCT(ISNUMBER(SEARCH(".Net",'Bench Data'!L2:L78))*('Bench Data'!D2:D78="RFD")) -> 0 | D12: =C12-B12 -> -8 | E12: =SUMPRODUCT(ISNUMBER(SEARCH(".Net",'BD Data'!C2:C165))*('BD Data'!N2:N165="Onboarded")) -> 0 | F12: =B12 -> 8 | G12: =IFERROR(E12/F12,0) -> 0 | H12: Watch
A13: Salesforce | B13: =SUMPRODUCT(ISNUMBER(SEARCH("Salesforce",'BD Data'!C2:C165))*1) -> 4 | C13: =SUMPRODUCT(ISNUMBER(SEARCH("Salesforce",'Bench Data'!L2:L78))*('Bench Data'!D2:D78="RFD")) -> 0 | D13: =C13-B13 -> -4 | E13: =SUMPRODUCT(ISNUMBER(SEARCH("Salesforce",'BD Data'!C2:C165))*('BD Data'!N2:N165="Onboarded")) -> 0 | F13: =B13 -> 4 | G13: =IFERROR(E13/F13,0) -> 0 | H13: Watch
A14: Android | B14: =SUMPRODUCT(ISNUMBER(SEARCH("Android",'BD Data'!C2:C165))*1) -> 4 | C14: =SUMPRODUCT(ISNUMBER(SEARCH("Android",'Bench Data'!L2:L78))*('Bench Data'!D2:D78="RFD")) -> 0 | D14: =C14-B14 -> -4 | E14: =SUMPRODUCT(ISNUMBER(SEARCH("Android",'BD Data'!C2:C165))*('BD Data'!N2:N165="Onboarded")) -> 0 | F14: =B14 -> 4 | G14: =IFERROR(E14/F14,0) -> 0 | H14: Watch
A15: SRE | B15: =SUMPRODUCT(ISNUMBER(SEARCH("SRE",'BD Data'!C2:C165))*1) -> 2 | C15: =SUMPRODUCT(ISNUMBER(SEARCH("SRE",'Bench Data'!L2:L78))*('Bench Data'!D2:D78="RFD")) -> 0 | D15: =C15-B15 -> -2 | E15: =SUMPRODUCT(ISNUMBER(SEARCH("SRE",'BD Data'!C2:C165))*('BD Data'!N2:N165="Onboarded")) -> 0 | F15: =B15 -> 2 | G15: =IFERROR(E15/F15,0) -> 0 | H15: Watch
A16: AI/ML | B16: =SUMPRODUCT(ISNUMBER(SEARCH("AI/ML",'BD Data'!C2:C165))*1) -> 2 | C16: =SUMPRODUCT(ISNUMBER(SEARCH("AI/ML",'Bench Data'!L2:L78))*('Bench Data'!D2:D78="RFD")) -> 0 | D16: =C16-B16 -> -2 | E16: =SUMPRODUCT(ISNUMBER(SEARCH("AI/ML",'BD Data'!C2:C165))*('BD Data'!N2:N165="Onboarded")) -> 0 | F16: =B16 -> 2 | G16: =IFERROR(E16/F16,0) -> 0 | H16: Emerging
A17: Data Engineer | B17: =SUMPRODUCT(ISNUMBER(SEARCH("Data",'BD Data'!C2:C165))*1) -> 8 | C17: =SUMPRODUCT(ISNUMBER(SEARCH("Data",'Bench Data'!L2:L78))*('Bench Data'!D2:D78="RFD")) -> 0 | D17: =C17-B17 -> -8 | E17: =SUMPRODUCT(ISNUMBER(SEARCH("Data",'BD Data'!C2:C165))*('BD Data'!N2:N165="Onboarded")) -> 0 | F17: =B17 -> 8 | G17: =IFERROR(E17/F17,0) -> 0 | H17: Emerging

Sheet BD Performance
A1: BD Performance — per-BD/recruiter scorecard
A2: Bench Interview metrics for BDs (Bench Intv Data tab) and Market metrics for Recruiters (Market Intv Data tab).
A4: BENCH BDs (from Bench Intv Data)
A5: BD Name | B5: Total Interviews | C5: Done | D5: Rescheduled | E5: Selected | F5: Rejected | G5: Selection Rate
A6: Veeru | B6: =COUNTIF('Bench Intv Data'!E2:E135,A6) -> 51 | C6: =COUNTIFS('Bench Intv Data'!E2:E135,A6,'Bench Intv Data'!G2:G135,"Done") -> 48 | D6: =COUNTIFS('Bench Intv Data'!E2:E135,A6,'Bench Intv Data'!G2:G135,"Rescheduled") -> 3 | E6: =SUMPRODUCT(('Bench Intv Data'!E2:E135=A6)*ISNUMBER(SEARCH("Selected",'Bench Intv Data'!I2:I135))) -> 27 | F6: =SUMPRODUCT(('Bench Intv Data'!E2:E135=A6)*ISNUMBER(SEARCH("Rejected",'Bench Intv Data'!I2:I135))) -> 14 | G6: =IFERROR(E6/(E6+F6),0) -> 0.65853659
A7: Ruchitha | B7: =COUNTIF('Bench Intv Data'!E2:E135,A7) -> 32 | C7: =COUNTIFS('Bench Intv Data'!E2:E135,A7,'Bench Intv Data'!G2:G135,"Done") -> 32 | D7: =COUNTIFS('Bench Intv Data'!E2:E135,A7,'Bench Intv Data'!G2:G135,"Rescheduled") -> 0 | E7: =SUMPRODUCT(('Bench Intv Data'!E2:E135=A7)*ISNUMBER(SEARCH("Selected",'Bench Intv Data'!I2:I135))) -> 19 | F7: =SUMPRODUCT(('Bench Intv Data'!E2:E135=A7)*ISNUMBER(SEARCH("Rejected",'Bench Intv Data'!I2:I135))) -> 4 | G7: =IFERROR(E7/(E7+F7),0) -> 0.82608696
A8: Thanishka | B8: =COUNTIF('Bench Intv Data'!E2:E135,A8) -> 23 | C8: =COUNTIFS('Bench Intv Data'!E2:E135,A8,'Bench Intv Data'!G2:G135,"Done") -> 19 | D8: =COUNTIFS('Bench Intv Data'!E2:E135,A8,'Bench Intv Data'!G2:G135,"Rescheduled") -> 4 | E8: =SUMPRODUCT(('Bench Intv Data'!E2:E135=A8)*ISNUMBER(SEARCH("Selected",'Bench Intv Data'!I2:I135))) -> 9 | F8: =SUMPRODUCT(('Bench Intv Data'!E2:E135=A8)*ISNUMBER(SEARCH("Rejected",'Bench Intv Data'!I2:I135))) -> 8 | G8: =IFERROR(E8/(E8+F8),0) -> 0.52941176
A9: Phoenix | B9: =COUNTIF('Bench Intv Data'!E2:E135,A9) -> 18 | C9: =COUNTIFS('Bench Intv Data'!E2:E135,A9,'Bench Intv Data'!G2:G135,"Done") -> 17 | D9: =COUNTIFS('Bench Intv Data'!E2:E135,A9,'Bench Intv Data'!G2:G135,"Rescheduled") -> 1 | E9: =SUMPRODUCT(('Bench Intv Data'!E2:E135=A9)*ISNUMBER(SEARCH("Selected",'Bench Intv Data'!I2:I135))) -> 7 | F9: =SUMPRODUCT(('Bench Intv Data'!E2:E135=A9)*ISNUMBER(SEARCH("Rejected",'Bench Intv Data'!I2:I135))) -> 5 | G9: =IFERROR(E9/(E9+F9),0) -> 0.58333333
A10: Sadiya | B10: =COUNTIF('Bench Intv Data'!E2:E135,A10) -> 10 | C10: =COUNTIFS('Bench Intv Data'!E2:E135,A10,'Bench Intv Data'!G2:G135,"Done") -> 6 | D10: =COUNTIFS('Bench Intv Data'!E2:E135,A10,'Bench Intv Data'!G2:G135,"Rescheduled") -> 4 | E10: =SUMPRODUCT(('Bench Intv Data'!E2:E135=A10)*ISNUMBER(SEARCH("Selected",'Bench Intv Data'!I2:I135))) -> 2 | F10: =SUMPRODUCT(('Bench Intv Data'!E2:E135=A10)*ISNUMBER(SEARCH("Rejected",'Bench Intv Data'!I2:I135))) -> 2 | G10: =IFERROR(E10/(E10+F10),0) -> 0.5
A13: MARKET RECRUITERS (from Market Intv Data)
A14: Recruiter | B14: Total Interviews | C14: Done | D14: Rescheduled | E14: Selected | F14: Rejected | G14: Selection Rate
A15: Reshma | B15: =COUNTIF('Market Intv Data'!F2:F36,A15) -> 15 | C15: — | D15: — | E15: =SUMPRODUCT(('Market Intv Data'!F2:F36=A15)*ISNUMBER(SEARCH("Select",'Market Intv Data'!G2:G36))) -> 4 | F15: =SUMPRODUCT(('Market Intv Data'!F2:F36=A15)*ISNUMBER(SEARCH("Reject",'Market Intv Data'!G2:G36))) -> 6 | G15: =IFERROR(E15/(E15+F15),0) -> 0.4
A16: Apoorva | B16: =COUNTIF('Market Intv Data'!F2:F36,A16) -> 11 | C16: — | D16: — | E16: =SUMPRODUCT(('Market Intv Data'!F2:F36=A16)*ISNUMBER(SEARCH("Select",'Market Intv Data'!G2:G36))) -> 0 | F16: =SUMPRODUCT(('Market Intv Data'!F2:F36=A16)*ISNUMBER(SEARCH("Reject",'Market Intv Data'!G2:G36))) -> 7 | G16: =IFERROR(E16/(E16+F16),0) -> 0
A17: Archana | B17: =COUNTIF('Market Intv Data'!F2:F36,A17) -> 6 | C17: — | D17: — | E17: =SUMPRODUCT(('Market Intv Data'!F2:F36=A17)*ISNUMBER(SEARCH("Select",'Market Intv Data'!G2:G36))) -> 1 | F17: =SUMPRODUCT(('Market Intv Data'!F2:F36=A17)*ISNUMBER(SEARCH("Reject",'Market Intv Data'!G2:G36))) -> 3 | G17: =IFERROR(E17/(E17+F17),0) -> 0.25
A18: Roshini | B18: =COUNTIF('Market Intv Data'!F2:F36,A18) -> 3 | C18: — | D18: — | E18: =SUMPRODUCT(('Market Intv Data'!F2:F36=A18)*ISNUMBER(SEARCH("Select",'Market Intv Data'!G2:G36))) -> 1 | F18: =SUMPRODUCT(('Market Intv Data'!F2:F36=A18)*ISNUMBER(SEARCH("Reject",'Market Intv Data'!G2:G36))) -> 2 | G18: =IFERROR(E18/(E18+F18),0) -> 0.33333333

Sheet Hard-to-Place
A1: Hard-to-Place Watchlist — bench resources with high interview count
A2: Top resources by interview count from Bench Intv Data. Investigate why they're not placing.
A4: Resource Name | B4: Interview Count | C4: Selected (any) | D4: Rejected (any) | E4: Bench Status | F4: Bench Rating
A5: Bushra Sultana | B5: =COUNTIF('Bench Intv Data'!C2:C135,A5) -> 10 | C5: =SUMPRODUCT(('Bench Intv Data'!C2:C135=A5)*ISNUMBER(SEARCH("Selected",'Bench Intv Data'!I2:I135))) -> 5 | D5: =SUMPRODUCT(('Bench Intv Data'!C2:C135=A5)*ISNUMBER(SEARCH("Rejected",'Bench Intv Data'!I2:I135))) -> 1 | E5: =IFERROR(INDEX('Bench Data'!D2:D78,MATCH(A5,'Bench Data'!F2:F78,0)),"Not in Bench") -> WFD | F5: =IFERROR(INDEX('Bench Data'!E2:E78,MATCH(A5,'Bench Data'!F2:F78,0)),"-") -> Asset
A6: Mohammed Rehan Y | B6: =COUNTIF('Bench Intv Data'!C2:C135,A6) -> 7 | C6: =SUMPRODUCT(('Bench Intv Data'!C2:C135=A6)*ISNUMBER(SEARCH("Selected",'Bench Intv Data'!I2:I135))) -> 3 | D6: =SUMPRODUCT(('Bench Intv Data'!C2:C135=A6)*ISNUMBER(SEARCH("Rejected",'Bench Intv Data'!I2:I135))) -> 0 | E6: =IFERROR(INDEX('Bench Data'!D2:D78,MATCH(A6,'Bench Data'!F2:F78,0)),"Not in Bench") -> RFD | F6: =IFERROR(INDEX('Bench Data'!E2:E78,MATCH(A6,'Bench Data'!F2:F78,0)),"-") -> Asset
A7: Arpitha N | B7: =COUNTIF('Bench Intv Data'!C2:C135,A7) -> 7 | C7: =SUMPRODUCT(('Bench Intv Data'!C2:C135=A7)*ISNUMBER(SEARCH("Selected",'Bench Intv Data'!I2:I135))) -> 5 | D7: =SUMPRODUCT(('Bench Intv Data'!C2:C135=A7)*ISNUMBER(SEARCH("Rejected",'Bench Intv Data'!I2:I135))) -> 1 | E7: =IFERROR(INDEX('Bench Data'!D2:D78,MATCH(A7,'Bench Data'!F2:F78,0)),"Not in Bench") -> RFD | F7: =IFERROR(INDEX('Bench Data'!E2:E78,MATCH(A7,'Bench Data'!F2:F78,0)),"-") -> Asset
A8: Adoni Meenakshi Naidu | B8: =COUNTIF('Bench Intv Data'!C2:C135,A8) -> 6 | C8: =SUMPRODUCT(('Bench Intv Data'!C2:C135=A8)*ISNUMBER(SEARCH("Selected",'Bench Intv Data'!I2:I135))) -> 3 | D8: =SUMPRODUCT(('Bench Intv Data'!C2:C135=A8)*ISNUMBER(SEARCH("Rejected",'Bench Intv Data'!I2:I135))) -> 2 | E8: =IFERROR(INDEX('Bench Data'!D2:D78,MATCH(A8,'Bench Data'!F2:F78,0)),"Not in Bench") -> RFD | F8: =IFERROR(INDEX('Bench Data'!E2:E78,MATCH(A8,'Bench Data'!F2:F78,0)),"-") -> Asset
A9: Srinivas G | B9: =COUNTIF('Bench Intv Data'!C2:C135,A9) -> 6 | C9: =SUMPRODUCT(('Bench Intv Data'!C2:C135=A9)*ISNUMBER(SEARCH("Selected",'Bench Intv Data'!I2:I135))) -> 5 | D9: =SUMPRODUCT(('Bench Intv Data'!C2:C135=A9)*ISNUMBER(SEARCH("Rejected",'Bench Intv Data'!I2:I135))) -> 1 | E9: =IFERROR(INDEX('Bench Data'!D2:D78,MATCH(A9,'Bench Data'!F2:F78,0)),"Not in Bench") -> Not in Bench | F9: =IFERROR(INDEX('Bench Data'!E2:E78,MATCH(A9,'Bench Data'!F2:F78,0)),"-") -> -
A10: Sandeep Kumar | B10: =COUNTIF('Bench Intv Data'!C2:C135,A10) -> 5 | C10: =SUMPRODUCT(('Bench Intv Data'!C2:C135=A10)*ISNUMBER(SEARCH("Selected",'Bench Intv Data'!I2:I135))) -> 3 | D10: =SUMPRODUCT(('Bench Intv Data'!C2:C135=A10)*ISNUMBER(SEARCH("Rejected",'Bench Intv Data'!I2:I135))) -> 1 | E10: =IFERROR(INDEX('Bench Data'!D2:D78,MATCH(A10,'Bench Data'!F2:F78,0)),"Not in Bench") -> WFD | F10: =IFERROR(INDEX('Bench Data'!E2:E78,MATCH(A10,'Bench Data'!F2:F78,0)),"-") -> Asset
A11: Rohan Paul | B11: =COUNTIF('Bench Intv Data'!C2:C135,A11) -> 5 | C11: =SUMPRODUCT(('Bench Intv Data'!C2:C135=A11)*ISNUMBER(SEARCH("Selected",'Bench Intv Data'!I2:I135))) -> 2 | D11: =SUMPRODUCT(('Bench Intv Data'!C2:C135=A11)*ISNUMBER(SEARCH("Rejected",'Bench Intv Data'!I2:I135))) -> 1 | E11: =IFERROR(INDEX('Bench Data'!D2:D78,MATCH(A11,'Bench Data'!F2:F78,0)),"Not in Bench") -> RFD | F11: =IFERROR(INDEX('Bench Data'!E2:E78,MATCH(A11,'Bench Data'!F2:F78,0)),"-") -> Asset
A12: Suramya S | B12: =COUNTIF('Bench Intv Data'!C2:C135,A12) -> 5 | C12: =SUMPRODUCT(('Bench Intv Data'!C2:C135=A12)*ISNUMBER(SEARCH("Selected",'Bench Intv Data'!I2:I135))) -> 2 | D12: =SUMPRODUCT(('Bench Intv Data'!C2:C135=A12)*ISNUMBER(SEARCH("Rejected",'Bench Intv Data'!I2:I135))) -> 0 | E12: =IFERROR(INDEX('Bench Data'!D2:D78,MATCH(A12,'Bench Data'!F2:F78,0)),"Not in Bench") -> RFD | F12: =IFERROR(INDEX('Bench Data'!E2:E78,MATCH(A12,'Bench Data'!F2:F78,0)),"-") -> Asset
A13: Bhaswat Abhishek Shandilya | B13: =COUNTIF('Bench Intv Data'!C2:C135,A13) -> 5 | C13: =SUMPRODUCT(('Bench Intv Data'!C2:C135=A13)*ISNUMBER(SEARCH("Selected",'Bench Intv Data'!I2:I135))) -> 1 | D13: =SUMPRODUCT(('Bench Intv Data'!C2:C135=A13)*ISNUMBER(SEARCH("Rejected",'Bench Intv Data'!I2:I135))) -> 1 | E13: =IFERROR(INDEX('Bench Data'!D2:D78,MATCH(A13,'Bench Data'!F2:F78,0)),"Not in Bench") -> RFD | F13: =IFERROR(INDEX('Bench Data'!E2:E78,MATCH(A13,'Bench Data'!F2:F78,0)),"-") -> Asset
A14: Vaishnavi Tandle | B14: =COUNTIF('Bench Intv Data'!C2:C135,A14) -> 4 | C14: =SUMPRODUCT(('Bench Intv Data'!C2:C135=A14)*ISNUMBER(SEARCH("Selected",'Bench Intv Data'!I2:I135))) -> 2 | D14: =SUMPRODUCT(('Bench Intv Data'!C2:C135=A14)*ISNUMBER(SEARCH("Rejected",'Bench Intv Data'!I2:I135))) -> 2 | E14: =IFERROR(INDEX('Bench Data'!D2:D78,MATCH(A14,'Bench Data'!F2:F78,0)),"Not in Bench") -> RFD | F14: =IFERROR(INDEX('Bench Data'!E2:E78,MATCH(A14,'Bench Data'!F2:F78,0)),"-") -> Asset
A15: Pooja Patil | B15: =COUNTIF('Bench Intv Data'!C2:C135,A15) -> 4 | C15: =SUMPRODUCT(('Bench Intv Data'!C2:C135=A15)*ISNUMBER(SEARCH("Selected",'Bench Intv Data'!I2:I135))) -> 3 | D15: =SUMPRODUCT(('Bench Intv Data'!C2:C135=A15)*ISNUMBER(SEARCH("Rejected",'Bench Intv Data'!I2:I135))) -> 1 | E15: =IFERROR(INDEX('Bench Data'!D2:D78,MATCH(A15,'Bench Data'!F2:F78,0)),"Not in Bench") -> WFD | F15: =IFERROR(INDEX('Bench Data'!E2:E78,MATCH(A15,'Bench Data'!F2:F78,0)),"-") -> Medium
A16: Deepak Kumar | B16: =COUNTIF('Bench Intv Data'!C2:C135,A16) -> 4 | C16: =SUMPRODUCT(('Bench Intv Data'!C2:C135=A16)*ISNUMBER(SEARCH("Selected",'Bench Intv Data'!I2:I135))) -> 2 | D16: =SUMPRODUCT(('Bench Intv Data'!C2:C135=A16)*ISNUMBER(SEARCH("Rejected",'Bench Intv Data'!I2:I135))) -> 1 | E16: =IFERROR(INDEX('Bench Data'!D2:D78,MATCH(A16,'Bench Data'!F2:F78,0)),"Not in Bench") -> RFD | F16: =IFERROR(INDEX('Bench Data'!E2:E78,MATCH(A16,'Bench Data'!F2:F78,0)),"-") -> Asset
A17: Nareshkannan N | B17: =COUNTIF('Bench Intv Data'!C2:C135,A17) -> 4 | C17: =SUMPRODUCT(('Bench Intv Data'!C2:C135=A17)*ISNUMBER(SEARCH("Selected",'Bench Intv Data'!I2:I135))) -> 1 | D17: =SUMPRODUCT(('Bench Intv Data'!C2:C135=A17)*ISNUMBER(SEARCH("Rejected",'Bench Intv Data'!I2:I135))) -> 1 | E17: =IFERROR(INDEX('Bench Data'!D2:D78,MATCH(A17,'Bench Data'!F2:F78,0)),"Not in Bench") -> RFD | F17: =IFERROR(INDEX('Bench Data'!E2:E78,MATCH(A17,'Bench Data'!F2:F78,0)),"-") -> Asset
A18: Shajeer Ali | B18: =COUNTIF('Bench Intv Data'!C2:C135,A18) -> 3 | C18: =SUMPRODUCT(('Bench Intv Data'!C2:C135=A18)*ISNUMBER(SEARCH("Selected",'Bench Intv Data'!I2:I135))) -> 2 | D18: =SUMPRODUCT(('Bench Intv Data'!C2:C135=A18)*ISNUMBER(SEARCH("Rejected",'Bench Intv Data'!I2:I135))) -> 0 | E18: =IFERROR(INDEX('Bench Data'!D2:D78,MATCH(A18,'Bench Data'!F2:F78,0)),"Not in Bench") -> RFD | F18: =IFERROR(INDEX('Bench Data'!E2:E78,MATCH(A18,'Bench Data'!F2:F78,0)),"-") -> Asset
A19: Sthita Prajna Satapathy | B19: =COUNTIF('Bench Intv Data'!C2:C135,A19) -> 3 | C19: =SUMPRODUCT(('Bench Intv Data'!C2:C135=A19)*ISNUMBER(SEARCH("Selected",'Bench Intv Data'!I2:I135))) -> 1 | D19: =SUMPRODUCT(('Bench Intv Data'!C2:C135=A19)*ISNUMBER(SEARCH("Rejected",'Bench Intv Data'!I2:I135))) -> 0 | E19: =IFERROR(INDEX('Bench Data'!D2:D78,MATCH(A19,'Bench Data'!F2:F78,0)),"Not in Bench") -> RFD | F19: =IFERROR(INDEX('Bench Data'!E2:E78,MATCH(A19,'Bench Data'!F2:F78,0)),"-") -> Asset

Sheet Bench vs Market
A1: Bench vs Market — sourcing head-to-head
A2: Compares outcomes by source from BD Data Source column.
A4: Metric | B4: Bench | C4: Market | D4: Verdict
A5: Submissions | B5: =COUNTIF('BD Data'!K2:K165,"Bench") -> 88 | C5: =COUNTIF('BD Data'!K2:K165,"Market") -> 66 | D5: =IF(B5>C5,"Bench leads",IF(C5>B5,"Market leads","Tied")) -> Bench leads
A6: Onboarded | B6: =COUNTIFS('BD Data'!K2:K165,"Bench",'BD Data'!N2:N165,"Onboarded") -> 4 | C6: =COUNTIFS('BD Data'!K2:K165,"Market",'BD Data'!N2:N165,"Onboarded") -> 0 | D6: =IF(B6>C6,"Bench leads",IF(C6>B6,"Market leads","Tied")) -> Bench leads
A7: Final Selected | B7: =COUNTIFS('BD Data'!K2:K165,"Bench",'BD Data'!N2:N165,"Final Select") -> 5 | C7: =COUNTIFS('BD Data'!K2:K165,"Market",'BD Data'!N2:N165,"Final Select") -> 1 | D7: =IF(B7>C7,"Bench leads",IF(C7>B7,"Market leads","Tied")) -> Bench leads
A8: Profile Rejected | B8: =COUNTIFS('BD Data'!K2:K165,"Bench",'BD Data'!N2:N165,"Profile Rejected") -> 26 | C8: =COUNTIFS('BD Data'!K2:K165,"Market",'BD Data'!N2:N165,"Profile Rejected") -> 30 | D8: =IF(B8>C8,"Bench leads",IF(C8>B8,"Market leads","Tied")) -> Market leads
A9: Lost / Deferred | B9: =COUNTIFS('BD Data'!K2:K165,"Bench",'BD Data'!N2:N165,"Lost / Deferred") -> 14 | C9: =COUNTIFS('BD Data'!K2:K165,"Market",'BD Data'!N2:N165,"Lost / Deferred") -> 19 | D9: =IF(B9>C9,"Bench leads",IF(C9>B9,"Market leads","Tied")) -> Market leads
A10: Active Pipeline | B10: =COUNTIFS('BD Data'!K2:K165,"Bench",'BD Data'!N2:N165,"Profile Shared")+COUNTIFS('BD Data'!K2:K165,"Bench",'BD Data'!N2:N165,"Awaiting Feedback")+COUNTIFS('BD Data'!K2:K165,"Bench",'BD Data'!N2:N165,"On Hold")+COUNTIFS('BD Data'!K2:K165,"Bench",'BD Data'!N2:N165,"Shortlisted")+COUNTIFS('BD Data'!K2:K165,"Bench",'BD Data'!N2:N165,"Final Select") -> 41 | C10: =COUNTIFS('BD Data'!K2:K165,"Market",'BD Data'!N2:N165,"Profile Shared")+COUNTIFS('BD Data'!K2:K165,"Market",'BD Data'!N2:N165,"Awaiting Feedback")+COUNTIFS('BD Data'!K2:K165,"Market",'BD Data'!N2:N165,"On Hold")+COUNTIFS('BD Data'!K2:K165,"Market",'BD Data'!N2:N165,"Shortlisted")+COUNTIFS('BD Data'!K2:K165,"Market",'BD Data'!N2:N165,"Final Select") -> 11 | D10: =IF(B10>C10,"Bench leads",IF(C10>B10,"Market leads","Tied")) -> Bench leads
A12: CONVERSION RATES
A13: Onboard Rate | B13: =IFERROR(B6/B5,0) -> 0.045454545 | C13: =IFERROR(C6/C5,0) -> 0 | D13: =IF(B13>C13,"Bench better",IF(C13>B13,"Market better","Tied")) -> Bench better
A14: Profile Reject Rate | B14: =IFERROR(B8/B5,0) -> 0.29545455 | C14: =IFERROR(C8/C5,0) -> 0.45454545 | D14: =IF(B14>C14,"Bench better",IF(C14>B14,"Market better","Tied")) -> Market better
A15: Lost/Deferred Rate | B15: =IFERROR(B9/B5,0) -> 0.15909091 | C15: =IFERROR(C9/C5,0) -> 0.28787879 | D15: =IF(B15>C15,"Bench better",IF(C15>B15,"Market better","Tied")) -> Market better
A16: Active Pipeline % | B16: =IFERROR(B10/B5,0) -> 0.46590909 | C16: =IFERROR(C10/C5,0) -> 0.16666667 | D16: =IF(B16>C16,"Bench better",IF(C16>B16,"Market better","Tied")) -> Bench better

Sheet BD Data
A1: En. Date | B1: Account | C1: Skill | D1: Sub Skill | E1: Exp. | F1: Budget LPM | G1: C. Typ | H1: C. Dur | I1: Wrk Mode | J1: Location | K1: Source | L1: Candidate | M1: LVL | N1: Status | O1: Scr/int Date
A2: 46093 | B2: Byteridge | C2: Angular | E2: 5+ | F2: 100000 | G2: C-C | H2: 6 | K2: Bench | L2: Shritee Das | N2: Onboarded | O2: 46094
A3: 46093 | B3: Kognivera | C3: React | E3: 3+ | G3: C-C | H3: 6 | I3: WFO | J3: BLR | K3: Bench | L3: Sandipan Deb | M3: L3 | N3: Onboarded | O3: 46098
A4: 46097 | B4: Geekyants | C4: Java | E4: 4+ | G4: C-C | H4: 12 | I4: WFO | J4: MUM | K4: Bench | L4: Pooja Patil | M4: L3 | N4: Final Select | O4: 4/14/2026
A5: 46105 | B5: Zecdata | C5: Java | E5: 2+ | G5: C-C | H5: 6 | I5: WFO | J5: BLR | K5: Bench | L5: Suramya S | M5: L1 | N5: Awaiting Feedback | O5: 4/17/2026
A6: 46108 | B6: Prodian | C6: JFSR | E6: 4+ | G6: C-C | H6: 6 | I6: WFO | J6: Chennai | K6: Bench | L6: Pradeep Kumar R | N6: Profile Shared
A7: 46111 | B7: XPO | C7: Python | E7: 8+ | G7: C-C | H7: 12 | I7: WFO | J7: PUNE | K7: Bench | L7: Abhijeet Sengar | M7: L2 | N7: Onboarded | O7: 46177
A8: 46111 | B8: XPO | C8: Python | E8: 8+ | G8: C-C | H8: 12 | I8: WFO | J8: PUNE | K8: Market | L8: Shubham Dahibhate | M8: L1 | N8: Offer Rejected | O8: 46177
A9: 46111 | B9: XPO | C9: Python | E9: 8+ | G9: C-C | H9: 12 | I9: WFO | J9: PUNE | K9: Market | L9: Shweta Pande | N9: Lost / Deferred
A10: 46113 | B10: Byteridge | C10: Java/GoLang | E10: 3 | G10: C-C | H10: 6 | I10: WFO | J10: BLR | K10: Market | L10: Mahalakshmi T | M10: S1 | N10: No Show | O10: 46299
A11: 46113 | B11: Byteridge | C11: Java/GoLang | E11: 2+ | G11: C-C | H11: 6 | I11: WFO | J11: BLR | K11: Market | L11: Muhil Anirudh | M11: S1 | N11: Profile Rejected | O11: 46299
A12: 46113 | B12: REBIT | C12: Java | E12: 4+ | G12: C-C | H12: 6 | I12: WFO | J12: BLR | K12: Bench | L12: Soumyadeep Das | M12: L1 | N12: Profile Rejected | O12: 46299
A13: 46113 | B13: REBIT | C13: Java | E13: 4+ | G13: C-C | H13: 6 | I13: WFO | J13: BLR | K13: Bench | L13: NareshKannan N | N13: Profile Shared
A14: 46113 | B14: REBIT | C14: Java | E14: 4 | G14: C-C | H14: 6 | I14: WFO | J14: BLR | K14: Bench | L14: Vidhika D Sirwani | N14: Profile Shared
A15: 46113 | B15: REBIT | C15: Java | E15: 3+ | G15: C-C | H15: 6 | I15: WFO | J15: BLR | K15: Bench | L15: Arpitha N | N15: Profile Shared
A16: 46113 | B16: REBIT | C16: Java | E16: 3+ | G16: C-C | H16: 6 | I16: WFO | J16: BLR | K16: Bench | L16: Adoni Meenakshi Naidu | M16: L1 | N16: Profile Rejected | O16: 4/20/2026
A17: 46113 | B17: REBIT | C17: Java | E17: 3+ | G17: C-C | H17: 6 | I17: WFO | J17: BLR | K17: Bench | L17: Sthita Prajna Satapathy | M17: L1 | N17: Interview
A18: 46113 | B18: REBIT | C18: Java | E18: 2+ | G18: C-C | H18: 6 | I18: WFO | J18: BLR | K18: Bench | L18: Suchetha J | N18: Profile Shared
A19: 46113 | B19: REBIT | C19: Java | E19: 2+ | G19: C-C | H19: 6 | I19: WFO | J19: BLR | K19: Bench | L19: Bushra Sultana | N19: Lost / Deferred
A20: 46113 | B20: REBIT | C20: Java | E20: 2+ | G20: C-C | H20: 6 | I20: WFO | J20: BLR | K20: Bench | L20: Cheluri Anand Reddy | N20: Lost / Deferred
A21: 46113 | B21: REBIT | C21: Java | E21: 4+ | G21: C-C | H21: 6 | I21: WFO | J21: Mumbai | K21: Bench | L21: Aditya Vijay Barathe | M21: L3 | N21: Final Select
A22: 46113 | B22: REBIT | C22: Java | E22: 4+ | G22: C-C | H22: 6 | I22: WFO | J22: Mumbai | K22: Bench | L22: Aishwarya Digambar Saywan | N22: Profile Shared
A23: 46113 | B23: REBIT | C23: Java | E23: 4 | G23: C-C | H23: 6 | I23: WFO | J23: Mumbai | K23: Bench | L23: Tapas Kumar Paul | N23: Profile Shared
A24: 46113 | B24: REBIT | C24: Java | E24: 3+ | G24: C-C | H24: 6 | I24: WFO | J24: Mumbai | K24: Bench | L24: Sandeep Kumar | M24: L3 | N24: Final Select
A25: 46113 | B25: REBIT | C25: Java | E25: 3+ | G25: C-C | H25: 6 | I25: WFO | J25: Mumbai | K25: Bench | L25: Akshay Santosh Achalkar | M25: L3 | N25: Final Select
A26: 46113 | B26: REBIT | C26: Java | E26: 3+ | G26: C-C | H26: 6 | I26: WFO | J26: Mumbai | K26: Bench | L26: Deepak Kumar | M26: L3 | N26: Profile Rejected
A27: 46113 | B27: REBIT | C27: Java | E27: 2+ | G27: C-C | H27: 6 | I27: WFO | J27: Mumbai | K27: Bench | L27: Srinivas G | M27: L1 | N27: Profile Rejected | O27: 46269
A28: 46113 | B28: REBIT | C28: Java | E28: 2+ | G28: C-C | H28: 6 | I28: WFO | J28: Mumbai | K28: Bench | L28: Pooja Patil | M28: L3 | N28: Profile Rejected | O28: 46299
A29: 46113 | B29: REBIT | C29: Java | E29: 2+ | G29: C-C | H29: 6 | I29: WFO | J29: Mumbai | K29: Bench | L29: Rahul Kumar Ranjan | M29: L1 | N29: Profile Rejected | O29: 46299
A30: 46113 | B30: XPO | C30: Python | E30: 8+ | G30: C-C | H30: 12 | I30: WFO | J30: PUNE | K30: Market | L30: Shakti Pratap Singh | N30: Lost / Deferred
A31: 46113 | B31: Material | C31: Netwrok Engineer | E31: 8+ | G31: C-C | H31: 6 | I31: WFO | J31: DELHI | K31: Market | L31: Abhijeet Anand | N31: Lost / Deferred
A32: 46114 | B32: Mangalam | C32: Salesforce | E32: 4+ | G32: C-C | H32: 6 | I32: Remote | J32: Ahmedabad | K32: Market | L32: Girish mededar | N32: Profile Rejected
A33: 46114 | B33: Mangalam | C33: Salesforce | E33: 4+ | G33: C-C | H33: 6 | I33: Remote | J33: Ahmedabad | K33: Market | L33: Arjit Pratap Singh | M33: L1 | N33: Profile Rejected | O33: 46085
A34: 46114 | B34: Mangalam | C34: Salesforce | E34: 4+ | G34: C-C | H34: 6 | I34: Remote | J34: Ahmedabad | K34: Market | L34: Navdeep Singh | N34: On Hold
A35: 46114 | B35: Mangalam | C35: Salesforce | E35: 3+ | G35: C-C | H35: 6 | I35: Remote | J35: Ahmedabad | K35: Market | L35: Bontha Gowthami | N35: Lost / Deferred
A36: 46114 | B36: Innovation M | C36: Java | E36: 3+ | G36: C-C | I36: WFO | J36: Gurgaon | K36: Bench | L36: Suramya | M36: S2 | N36: On Hold
A37: 46114 | B37: Innovation M | C37: Java | E37: 3+ | G37: C-C | I37: WFO | J37: Gurgaon | K37: Bench | L37: Rohan Paul | M37: S2 | N37: On Hold
A38: 46114 | B38: Innovation M | C38: Java | E38: 3+ | G38: C-C | I38: WFO | J38: Gurgaon | K38: Bench | L38: Raj Singh Bhadauria | M38: S2 | N38: On Hold
A39: 46114 | B39: Innovation M | C39: Java | E39: 3+ | G39: C-C | I39: WFO | J39: Gurgaon | K39: Bench | L39: Pratibha Yogesh Kharwar | M39: S2 | N39: On Hold
A40: 46114 | B40: Innovation M | C40: Java | E40: 3+ | G40: C-C | I40: WFO | J40: Gurgaon | K40: Bench | L40: Sandeep Kumar | M40: S2 | N40: Profile Rejected
A41: 46114 | B41: Xebia | C41: Java | E41: 3+ | G41: C-C | H41: 6 | I41: WFO | J41: BLR | K41: Bench | L41: Adoni | M41: L1 | N41: Profile Rejected | O41: 46115
A42: 46114 | B42: Xebia | C42: Java | E42: 3+ | G42: C-C | H42: 6 | I42: WFO | J42: BLR | K42: Bench | L42: Arpita | M42: L1 | N42: On Hold | O42: 46115
A43: 46114 | B43: Xebia | C43: Java | E43: 3+ | G43: C-C | H43: 6 | I43: WFO | J43: BLR | K43: Bench | L43: Bushra | N43: On Hold | O43: 46135
A44: 46115 | B44: Ahana IT | C44: Data Support Engineer | E44: 4+ | G44: C-C | H44: 6 | I44: WFO | J44: BLR | K44: Market | L44: Giriraj Santosh Wankhede | N44: Lost / Deferred
A45: 46115 | B45: Ahana IT | C45: Data Support Engineer | E45: 4+ | G45: C-C | H45: 6 | I45: WFO | J45: BLR | K45: Market | L45: Mahitha | N45: Lost / Deferred
A46: 46115 | B46: Ahana IT | C46: Data Support Engineer | E46: 4+ | G46: C-C | H46: 6 | I46: WFO | J46: BLR | K46: Market | L46: Sanket Bandal | M46: L2 | N46: Final Select | O46: 4/15/2026
A47: 46115 | B47: Mangalam | C47: Data Warehouse | E47: 7+ | G47: C-C | H47: 6 | I47: Remote | J47: Ahmedabad | K47: Market | N47: On Hold
A48: 46114 | B48: Ahana IT | C48: Data Support Engineer | E48: 4+ | G48: C-C | H48: 6 | I48: WFO | J48: BLR | K48: Market | L48: Shantanu Hingane | M48: L1 | N48: No Show | O48: 46085
A49: 46114 | B49: Ahana IT | C49: Data Support Engineer | E49: 4+ | G49: C-C | H49: 6 | I49: WFO | J49: BLR | K49: Market | L49: Ruturaj Mane | N49: Lost / Deferred
A50: 46118 | B50: Byteridge | C50: .Net FSD | E50: 3+ | F50: 150000 | G50: C-C | H50: 6 | I50: Remote | N50: Requirement Received
A51: 46119 | B51: NPCI | C51: SRE | E51: 5+ | G51: C-C | H51: 6 | I51: WFO | J51: HYD | K51: Market | L51: Salman Basha | N51: Lost / Deferred
A52: 46119 | B52: NPCI | C52: SRE | E52: 7+ | G52: C-C | H52: 6 | I52: WFO | J52: HYD | K52: Market | L52: Sairam | M52: L1 | N52: Screening Scheduled | O52: 4/23/2026
A53: 46121 | B53: Neosoft | C53: JFSR | E53: 4+ | G53: C-C | H53: 6 | I53: WFO | J53: Gurugram | K53: Bench | L53: Mohammed Rehan Y | N53: Lost / Deferred
A54: 46121 | B54: Neosoft | C54: JFSR | E54: 4+ | G54: C-C | H54: 6 | I54: WFO | J54: Gurugram | K54: Bench | L54: Sunil K | N54: Lost / Deferred
A55: 46121 | B55: Neosoft | C55: JFSR | E55: 4+ | G55: C-C | H55: 6 | I55: WFO | J55: Gurugram | K55: Bench | L55: Ganesh S | N55: Lost / Deferred
A56: 46121 | B56: Tarams | C56: Python | E56: 1+ | F56: 80000 | G56: C-C | H56: 6 | I56: WFO | J56: BLR | K56: Market | L56: Vignesh R | N56: Lost / Deferred
A57: 46121 | B57: Tarams | C57: Python | E57: 1+ | F57: 80000 | G57: C-C | H57: 6 | I57: WFO | J57: BLR | K57: Market | L57: Sangeetha | N57: Lost / Deferred
A58: 46121 | B58: Tarams | C58: Python | E58: 1+ | F58: 72000 | G58: C-C | H58: 6 | I58: WFO | J58: BLR | K58: Market | L58: Parsuram Das | N58: Lost / Deferred
A59: 46122 | B59: Zecdata | C59: React | E59: 3+ | F59: 85000 | G59: C-C | H59: 6 | I59: WFO | J59: BLR | K59: Bench | L59: Mohammed Rehan Y | M59: L1 | N59: Profile Rejected | O59: 4/14/2026
A60: 46122 | B60: Zecdata | C60: React | E60: 3+ | F60: 85000 | G60: C-C | H60: 6 | I60: WFO | J60: BLR | K60: Bench | L60: Sunil K | N60: Lost / Deferred
A61: 46122 | B61: Zecdata | C61: React | E61: 3+ | F61: 85000 | G61: C-C | H61: 6 | I61: WFO | J61: BLR | K61: Bench | L61: Ganesh S | M61: L1 | N61: Profile Rejected | O61: 4/14/2026
A62: 46122 | B62: Zecdata | C62: React | E62: 3+ | F62: 85000 | G62: C-C | H62: 6 | I62: WFO | J62: BLR | K62: Bench | L62: Janani Muthuselvam | N62: Lost / Deferred
A63: 46121 | B63: NeoVeda Tech | C63: Java | E63: 4+ | G63: C-C | H63: 6 | I63: WFO | K63: Bench | L63: Aditya | M63: S1 | N63: Lost / Deferred
A64: 46121 | B64: XPO | C64: Python | E64: 5+ | G64: C-C | H64: 6 | I64: WFO | J64: PUNE | K64: Market | L64: Anand | N64: Lost / Deferred
A65: 46121 | B65: XPO | C65: Python | E65: 5+ | G65: C-C | K65: Market | L65: Swapnil | M65: L1 | N65: Profile Rejected
A66: 46121 | B66: Byteridge | C66: Java/GoLang | E66: 2+ | G66: C-C | H66: 6 | I66: WFO | J66: BLR | K66: Market | L66: Sai Kowshik Keerthipati | M66: S1 | N66: Profile Rejected | O66: 46125
A67: 46121 | B67: Byteridge | C67: Java/GoLang | E67: 2+ | G67: C-C | H67: 6 | I67: WFO | J67: BLR | K67: Market | L67: Abdul Wasiv H | M67: S1 | N67: No Show | O67: 46125
A68: 46121 | B68: Byteridge | C68: .Net | E68: 3+ | F68: 150000 | G68: C-C | H68: 6 | I68: Remote | K68: Market | L68: Saurabh Soni | N68: No Show | O68: 4/13/2026
A69: 46121 | B69: Byteridge | C69: .Net | E69: 3+ | F69: 150000 | G69: C-C | H69: 6 | I69: Remote | K69: Market | L69: Bisweswar Das | N69: On Hold
A70: 46121 | B70: Byteridge | C70: .Net | E70: 3+ | F70: 150000 | G70: C-C | H70: 6 | I70: Remote | K70: Market | L70: Ravish Singh | N70: Profile Rejected | O70: 4/13/2026
A71: 46125 | B71: Leena.ai | C71: QA | E71: 3+ | F71: 100000 | G71: C-C | H71: 6 | I71: WFO | J71: Gurgaon | K71: Bench | L71: Shubham | N71: Onboarded | O71: 4/13/2026
A72: 46125 | B72: Ellow.io | C72: React | E72: 4+ | G72: C-C | H72: 6 | I72: Hybrid | J72: Trivandrum | K72: Bench | L72: Mohammed Rehan Y | N72: Profile Rejected
A73: 46125 | B73: GeekyAnts | C73: Java | E73: 4+ | G73: C-C | H73: 6 | I73: WFO | J73: BLR | K73: Bench | L73: Arpitha N | M73: S1 | N73: Shortlisted
A74: 46125 | B74: GeekyAnts | C74: Java | E74: 4+ | G74: C-C | H74: 6 | I74: WFO | J74: BLR | K74: Bench | L74: Tapas Kumar Paul | M74: S1 | N74: Profile Rejected | O74: 4/14/2026
A75: 46125 | B75: GeekyAnts | C75: Java | E75: 4+ | G75: C-C | H75: 6 | I75: WFO | J75: BLR | K75: Bench | L75: Swati G Madiwalar | M75: S1 | N75: Profile Rejected | O75: 4/14/2026
A76: 46125 | B76: GeekyAnts | C76: Java | E76: 4+ | G76: C-C | H76: 6 | I76: WFO | J76: BLR | K76: Bench | L76: Manoj T | M76: S1 | N76: Shortlisted
A77: 46120 | B77: Neosoft | C77: React | E77: 5 | F77: 100000 | G77: C-C | H77: 6 | I77: WFO | J77: Gurugram | K77: Market | L77: Priyabrat | M77: S1 | N77: Profile Rejected | O77: 46125
A78: 46120 | B78: Neosoft | C78: React | E78: 5 | F78: 100000 | G78: C-C | H78: 6 | I78: WFO | J78: Gurugram | K78: Market | L78: Rahul Nagar | M78: S1 | N78: Profile Rejected | O78: 46125
A79: 46120 | B79: Neosoft | C79: React | E79: 4+ | F79: 95000 | G79: C-C | H79: 6 | I79: WFO | J79: Gurugram | K79: Market | L79: Satyam Gupta | M79: L1 | N79: Lost / Deferred
A80: 46125 | B80: XPO | C80: Python | E80: 5+ | G80: C-C | H80: 6 | I80: WFO | J80: PUNE | K80: Market | L80: Shekhar Lashkari | M80: L1 | N80: Profile Rejected | O80: 4/14/2026
A81: 46125 | B81: XPO | C81: Python | E81: 5+ | G81: C-C | H81: 6 | I81: WFO | J81: PUNE | K81: Market | L81: Ajmal Hossain Sarkar | M81: L1 | N81: Profile Rejected | O81: 4/14/2026
A82: 46125 | B82: XPO | C82: Python | E82: 5+ | G82: C-C | H82: 6 | I82: WFO | J82: PUNE | K82: Market | L82: Amit Rupwate | N82: Profile Rejected
A83: 46125 | B83: Tarams | C83: Python | E83: 1+ | G83: C-C | H83: 6 | I83: WFO | J83: BLR | K83: Market | L83: Nikhil S | N83: Lost / Deferred
A84: 46125 | B84: Tarams | C84: Python | E84: 1+ | G84: C-C | H84: 6 | I84: WFO | J84: BLR | K84: Market | L84: Charitha Methri | N84: Lost / Deferred
A85: 46126 | B85: Zecdata | C85: Java | E85: 4+ | F85: 95000 | G85: C-C | H85: 6 | I85: Remote | K85: Bench | L85: Arpitha N | M85: L1 | N85: Profile Rejected | O85: 4/16/2026
A86: 46126 | B86: Zecdata | C86: Java | E86: 4+ | F86: 95000 | G86: C-C | H86: 6 | I86: Remote | K86: Bench | L86: Bhaswat Abhishek Shandilya | M86: L1 | N86: Profile Rejected | O86: 4/16/2026
A87: 46126 | B87: 1CHB | C87: Node | E87: 4+ | G87: C-C | H87: 6 | I87: WFO | J87: CHN | K87: Bench | L87: Mohammed Rehan Y | M87: L1 | N87: Profile Rejected | O87: 4/15/2026
A88: 46126 | B88: 1CHB | C88: Node | E88: 4+ | G88: C-C | H88: 6 | I88: WFO | J88: CHN | K88: Bench | L88: Sunil K | M88: L1 | N88: Profile Rejected | O88: 4/15/2026
A89: 46126 | B89: Byteridge | C89: GoLang | E89: 2+ | F89: 1,33,000/- | G89: C-C | H89: 6 | I89: WFO | J89: BLR | K89: Market | L89: Tirtha Jyoti Bol | M89: L3 | N89: Profile Rejected | O89: 4/22/2026
A90: 46126 | B90: Byteridge | C90: GoLang | E90: 2+ | F90: 95,000/- | G90: C-C | H90: 6 | I90: WFO | J90: BLR | K90: Market | L90: Pratik Chunkikar | M90: S2 | N90: Profile Rejected | O90: 4/15/2026
A92: 46126 | B92: Byteridge | C92: GoLang | E92: 2+ | F92: 112000 | G92: C-C | H92: 6 | I92: WFO | J92: BLR | K92: Market | L92: Ashutosh Srivastava | M92: S2 | N92: Profile Rejected | O92: 4/15/2026
A94: 46126 | B94: ARS Traffic | C94: .NET | E94: 5+ | G94: C-C | H94: 6 | I94: WFO | J94: Trivandrum | N94: Requirement Shared
A95: 46126 | B95: Neo Soft | C95: Node.js | E95: 7+ | N95: Lost / Deferred
A96: 46127 | B96: Xebia | C96: Java | E96: 3+ | F96: 120000 | G96: C-C | H96: 6 | I96: WFO | J96: MUM | K96: Bench | L96: Adoni Meenakshi Naidu | N96: Profile Rejected | O96: 4/16/2026
A97: 46127 | B97: Xebia | C97: Java | E97: 3+ | F97: 120000 | G97: C-C | H97: 6 | I97: WFO | J97: MUM | K97: Bench | L97: Saurin Kumar Ghosh | N97: Profile Shared
A98: 46127 | B98: Xebia | C98: Java | E98: 3+ | F98: 120000 | G98: C-C | H98: 6 | I98: WFO | J98: MUM | K98: Bench | L98: Bushra Sultana | N98: Final Select | O98: 4/21/2026
A99: 46127 | B99: Xebia | C99: Java | E99: 3+ | F99: 120000 | G99: C-C | H99: 6 | I99: WFO | J99: MUM | K99: Bench | L99: Paromita Biswas | N99: Profile Shared
A100: 46127 | B100: Neo Soft | C100: Drupal | E100: 5+ | N100: Lost / Deferred
A101: 46127 | B101: Deservely | C101: Java | E101: 5 | G101: C-C | H101: 6 | I101: WFO | J101: BLR | K101: Bench | L101: Ravindra Balkrushna Sonawane | N101: Lost / Deferred
A102: 46127 | B102: Deservely | C102: Java | E102: 5 | G102: C-C | H102: 6 | I102: WFO | J102: BLR | K102: Bench | L102: Arpitha N | N102: Lost / Deferred
...

Sheet Bench Data
A1: No | B1: Batch | C1: Source | D1: Status | E1: Rating | F1: Name | G1: Contact Number | H1: Official Mail ID | I1: Personal Mail ID | J1: YOE - A | K1: YOE - P | L1: Skill Set | M1: No of Interviews | N1: YOP
A2: 1 | B2: 17th Apr 2025 | C2: Bench | D2: RFD | E2: Asset | F2: Pratibha Yogesh Kharwar | G2: 7972549038 | H2: NA | I2: kharwarpy@rknec.edu | J2: 2.1 | K2: 3.1 | L2: Java + SB | M2: 13 | N2: 2022
A3: 2 | B3: 16th Jun 2025 | C3: Bench | D3: RFD | E3: Asset | F3: Furkan Ali Zafari | G3: 7518817786 | H3: NA | I3: furkan201296@gmail.com | J3: 2.1 | K3: 3.2 | L3: JFSR | M3: 6 | N3: 2021
A4: 3 | B4: 16th Jun 2025 | C4: Bench | D4: RFD | E4: Asset | F4: Cheluri Anand Reddy | G4: 7993098031 | H4: NA | I4: reddyanand1403@gmail.com | J4: 2.1 | K4: 3.4 | L4: Java + SB | M4: 5 | N4: 2023
A5: 4 | B5: 23rd Jun 2025 | C5: Bench | D5: RFD | E5: Medium | F5: E Kiruthivaas | G5: 9360425543 | H5: NA | I5: dev.kiruthi@gmail.com | J5: 2.2 | K5: 2.6 | L5: React JS | M5: 7 | N5: 2023
A6: 5 | B6: 23rd Jun 2025 | C6: Bench | D6: RFD | E6: Medium | F6: Janani Muthuselvam | G6: 8838311540 | H6: NA | I6: jananivm06@gmail.com | J6: 2.1 | K6: 2.1 | L6: React JS | M6: 3 | N6: 2020
A7: 6 | B7: 23rd Jun 2025 | C7: Bench | D7: RFD | E7: Medium | F7: Rahul Shibi S A | G7: 9487920544 | H7: NA | I7: rahulshibi22@gmail.com | J7: 2.1 | K7: 2.4 | L7: React JS | M7: 1 | N7: 2021
A8: 7 | B8: 16th Jul 2025 | C8: Bench | D8: RFD | E8: Lialibility | F8: Lakku Jayaprakash Reddy | G8: 7893137299 | H8: NA | I8: lakkujayaprakash@gmail.com | J8: 3.2 | K8: 3.2 | L8: Java + SB | M8: 1 | N8: 2021
A9: 8 | B9: 16th Jul 2025 | C9: Bench | D9: RFD | E9: Medium | F9: Manoj T | G9: 9844251966 | H9: NA | I9: manojthangarajm@gmail.com | J9: 3.3 | K9: 3.2 | L9: Java + SB | M9: 4 | N9: 2022
A10: 9 | B10: 16th Jul 2025 | C10: Bench | D10: WFD | E10: Medium | F10: Pooja Patil | G10: 6362794142 | H10: NA | I10: poojachapatil@gmail.com | J10: 3.3 | K10: 3.2 | L10: Java + SB | M10: 6 | N10: 2021
A11: 10 | B11: 16th Jul 2025 | C11: Bench | D11: RFD | E11: Medium | F11: Raj Singh Bhadauria | G11: 8780459376 | H11: NA | I11: rajsinghbhadauria194@gmail.com | J11: 3.1 | K11: 3.1 | L11: JFSR | M11: 3 | N11: 2023
A12: 11 | B12: 16th Jul 2025 | C12: Bench | D12: RFD | E12: Asset | F12: Sudha Kumari Gurung | G12: 6393803753 | H12: NA | I12: Sudhagrg2102@gmail.com | J12: 2.1 | K12: 3.3 | L12: JFSR | M12: 7 | N12: 2022
A13: 12 | B13: 16th Jul 2025 | C13: Bench | D13: RFD | E13: Medium | F13: Aamir Abdullah Khan | G13: 7031509368 | H13: NA | I13: aamirkhan19994u@gmail.com | J13: 2.1 | K13: 3.4 | L13: Java + SB | M13: 2 | N13: 2023
... A40: 39 | B40: 29th Dec 2025 | C40: Bench | D40: RFD | E40: Asset | F40: Souraj Das | G40: 7585082936 | H40: NA | I40: sourajdas15@gmail.com | J40: 0.6 | K40: 0.6 | L40: React JS | M40: 0 | N40: 2025
A41: 40 | B41: 15th Dec 2025 | C41: Bench | D41: RFD | F41: Manoranjan Das | G41: 9178832411 | H41: NA | I41: dmanoranjan090@gmail.com | J41: 3.2 | K41: 3.2 | L41: Java + SB | N41: 2023
A42: 41 | B42: 15th Dec 2025 | C42: Bench | D42: RFD | F42: Bissaihgari Janardhan Reddy | G42: 9380506027 | H42: NA | I42: bsjanardhanreddy@gmail.com | J42: 3.4 | K42: 3.4 | L42: Java + SB | N42: 2018
A43: 42 | B43: 15th Dec 2025 | C43: Bench | D43: NA | E43: Medium | F43: Sana Jagdish Sachdeva | G43: 9016261345 | H43: NA | I43: Sana.sachdeva04@gmail.com | J43: 3.1 | K43: 3.1 | L43: Java + SB | N43: 2023
A44: 43 | B44: 15th Dec 2025 | C44: Bench | D44: RFD | F44: Arijit Sow | G44: 9635196051 | H44: NA | I44: arijit.sow@gmail.com | J44: 3.5 | K44: 3.5 | L44: Java + SB | N44: 2023
A45: 44 | B45: 15th Dec 2025 | C45: Bench | D45: RFD | F45: Suresh | G45: 8310245356 | H45: NA | I45: sureshaydnal@gmail.com | J45: 3.5 | K45: 3.5 | L45: Java + SB | N45: 2023
A46: 45 | B46: 15th Dec 2025 | C46: Bench | D46: RFD | F46: B Pavan Kumar | G46: 7288812161 | H46: NA | I46: budurupavankumar268@gmail.com | J46: 3.5 | K46: 3.5 | L46: Java + SB | N46: 2021
A47: 46 | B47: 15th Dec 2025 | C47: Bench | D47: RFD | F47: Mayank Sinha | G47: 8197623998 | H47: NA | I47: mayank.s119698@gmail.com | J47: 3.1 | K47: 3.1 | L47: Java + SB | N47: 2023
A48: 47 | B48: 15th Dec 2025 | C48: Bench | D48: RFD | F48: Vaibhav Sen | G48: 8871975748 | H48: NA | I48: senvaibhav36@gmail.com | J48: 3.2 | K48: 3.2 | L48: Java + SB | N48: 2023
A49: 48 | B49: 15th Dec 2025 | C49: Bench | D49: RFD | F49: Tanmoy Pramanick | G49: 7978557446 | H49: NA | I49: pramanickt15@gmail.com | J49: 3.1 | K49: 3.1 | L49: Java + SB | N49: 2020
A50: 49 | C50: B2B | D50: RFD | E50: Asset | F50: Bhaswat Abhishek Shandilya | G50: 7022363693 | H50: abhishek.shandilya@testyantra.in | I50: Shandilya.bhaswat@gmail.com | J50: 2.4 | K50: 4.1 | L50: Java + SB | M50: 1 | N50: 2019
A51: 50 | C51: B2B | D51: RFD | E51: Lialibility | F51: Subhajit Saha | G51: 8617529136 | H51: subhajit.s@testyantra.in | I51: 1999subhajitsaha@gmail.com | J51: 3.1 | K51: 3.4 | L51: Java + SB | M51: 4 | N51: 2022
A52: 51 | C52: B2B | D52: RFD | E52: Asset | F52: Vidhika D Sirwani | G52: 9740072180 | H52: vidhika.d@testyantra.in | I52: vidhika1543@gmail.com | J52: 3.7 | K52: 3.7 | L52: Java + SB | M52: 7 | N52: 2019
A53: 52 | C53: B2B | D53: RFD | E53: Asset | F53: Tapas Kumar Paul | G53: 8867005735 | H53: tapas.k@testyantra.in | I53: tapaspaul6262@gmail.com | J53: 4.3 | K53: 4.3 | L53: Java + SB | M53: 11 | N53: 2019
A54: 53 | C54: B2B | D54: RFD | E54: Asset | F54: Rahul Rajan Baskaran | G54: 9345852506 | H54: rahul.r@testyantra.co.in | I54: brahulrajan0506@gmail.com | J54: 3.4 | K54: 3.4 | L54: Java + SB | M54: 4 | N54: 2022
A55: 54 | C55: B2B | D55: RFD | E55: Asset | F55: Deepak Kumar | G55: 8789267097 | H55: deepak.kumar@testyantra.in | I55: deepakmehta2401@gmail.com | J55: 3.4 | K55: 3.4 | L55: Java + SB | M55: 6 | N55: 2022
A56: 55 | C56: B2B | D56: NA | E56: Asset | F56: Akshay Santosh Achalkar | G56: 9664364098 | H56: akshay.s@testyantra.co.in | I56: akshayachalkar@gmail.com | J56: 3.2 | K56: 3.2 | L56: Java + SB | M56: 5 | N56: 2014
A57: 56 | C57: B2B | D57: RFD | E57: Asset | F57: Shajeer Ali | G57: 7306028719 | H57: shajeer.a@testyantra.in | I57: shajeerali.saleem@gmail.com | J57: 3 | K57: 3 | L57: React JS | M57: 3 | N57: 2023
A58: 57 | C58: B2B | D58: RFD | E58: Asset | F58: Sthita Prajna Satapathy | G58: 9938464578 | H58: sthita.p@testyantra.co.in | I58: sthitaprajna9938@gmail.com | J58: 3.1 | K58: 3.1 | L58: Java + SB | M58: 5 | N58: 2019
A59: 58 | C59: B2B | D59: RFD | E59: Asset | F59: Soumyadeep Das | G59: 7477361693 | H59: soumyadeep.d@testyantra.co.in | I59: soumyaon7@gmail.com | J59: 3.3 | K59: 3.3 | L59: Java + SB | M59: 8 | N59: 2021
A60: 59 | C60: B2B | D60: RFD | E60: Asset | F60: Swati G Madiwalar | G60: 8296590838 | H60: swati.g@testyantra.co.in | I60: swatigmadiwalar@gmail.com | J60: 3 | K60: 3 | L60: Java + SB | M60: 4 | N60: 2019
A61: 60 | C61: B2B | D61: RFD | E61: Asset | F61: Ganesh S | G61: 8680055956 | H61: ganesh.s@testyantra.co.in | I61: ganeshthegan5237@gmail.com | J61: 2.11 | K61: 2.11 | L61: React JS | M61: 5 | N61: 2022
... A77: 76 | C77: B2B | D77: RFD | E77: Asset | F77: Saransh Vijay | G77: 9414490041 | H77: saransh.v@testyantra.in | I77: saransh.vijay@gmail.com | J77: 4.2 | K77: 4.2 | L77: Java + SB | M77: 0 | N77: 2021
A78: 77 | C78: B2B | D78: RFD | E78: Asset | F78: Priyanka Ramnath Belote | G78: 9637886063 | H78: priyanka.r@testyantra.in | I78: priyankabelote1996@gmail.com | J78: 4.1 | K78: 4.1 | L78: Java + SB | N78: 2020

Sheet Bench Intv Data
A1: Date | B1: Time | C1: Resources Name | D1: Client Name | E1: BD Name | F1: Assigned To | G1: Status | H1: Sample Questions | I1: Feedback
A2: 46113 | B2: 0.625 | C2: Niranjan Balaji N | D2: Prodian(L-1) | E2: Thanishka | F2: Sumeet | G2: Rescheduled | H2: Rescheduled | I2: Rescheduled
A3: 46113 | B3: 0.64583333 | C3: Aishwarya Digambar Saywan | D3: Expand My Business(L-5) | E3: Phoenix | F3: Sumeet | G3: Rescheduled | H3: Rescheduled | I3: Rescheduled
A4: 46113 | B4: 0.64583333 | C4: Mohammed Rehan Y | D4: Expand My Business(L-1) | E4: Phoenix | F4: Abhijit | G4: Done | H4: Done | I4: On Hold
A5: 46113 | B5: 0.66666667 | C5: Sandeep Kumar | D5: InnovationM(Screening) | E5: Veeru | F5: Sumeet | G5: Done | H5: Screening | I5: Selected Screening
A6: 46113 | B6: 0.66666667 | C6: Shajeer Ali | D6: Expand My Business(Screening) | E6: Phoenix | F6: Abhijit | G6: Done | H6: Done | I6: Selected Screening
A7: 46113 | B7: 0.6875 | C7: Abhijeet Sengar | D7: XPO(L-1) | E7: Ruchitha | F7: Sumeet | G7: Done | H7: NA | I7: Selected L2
A8: 46113 | B8: 0.70833333 | C8: Kiruthivaas E | D8: Expand My Business(Screening) | E8: Phoenix | F8: Abhijit | G8: Done | H8: Done | I8: Rejected Screening
A9: 46113 | B9: 0.72916667 | C9: Shreya Tripathi | D9: Expand My Business(Screening) | E9: Phoenix | F9: Abhijit | G9: Done | H9: Done | I9: Selected Screening
A10: 46113 | B10: 0.79166667 | C10: Rohan Paul | D10: InnovationM(L-1) | E10: Veeru | F10: Sumeet | G10: Rescheduled | H10: Rescheduled | I10: Rescheduled
A11: 46113 | B11: 0.83333333 | C11: Pratibha Yogesh Kharwar | D11: InnovationM(L-1) | E11: Veeru | F11: Sumeet | G11: Done | H11: Done | I11: Selected L1
A12: 46113 | B12: 0.875 | C12: Raj Singh Bhadauria | D12: InnovationM(L-1) | E12: Veeru | F12: Sumeet | G12: Done | H12: Done | I12: Selected L1
A13: 46113 | B13: 0.875 | C13: Sandeep Kumar | D13: InnovationM(L-1) | E13: Veeru | F13: Sumeet | G13: Rescheduled | H13: Rescheduled | I13: Rescheduled
... A64: 46125 | B64: 0.5625 | C64: Suchetha J | D64: Medimpact(L-1) | E64: Veeru | F64: Ariprasath | G64: Done | H64: Done | I64: Rejected L1
A65: 46125 | B65: F2F | C65: Bushra Sultana | D65: Medimpact(L-3 HR) | E65: Veeru | F65: Ariprasath | G65: Done | H65: Done | I65: Rejected F2F
A66: 46125 | B66: 0.64583333 | C66: Srinivas G | D66: Medimpact(L-1) | E66: Veeru | F66: Ariprasath | G66: Done | H66: Done | I66: Selected L1
A67: 46125 | B67: 0.64583333 | C67: Sudha Kumari Gurung | D67: Medimpact(Online Test) | E67: Veeru | F67: Ariprasath | G67: Done | H67: Online Test | I67: Rejected Online Test
A68: 46125 | B68: 0.64583333 | C68: Kunda Venkata Krishnaveni | D68: Medimpact(Online Test) | E68: Veeru | F68: Ariprasath | G68: Done | H68: Online Test | I68: Selected Online Test
A69: 46125 | B69: 0.64583333 | C69: Vaishnavi Hokrana | D69: Medimpact(Online Test) | E69: Veeru | F69: Ariprasath | G69: Done | H69: Online Test | I69: Selected Online Test
A70: 46125 | B70: 0.64583333 | C70: Ganesh S | D70: Zecdata(AI Screening) | E70: Veeru | F70: Ariprasath | G70: Done | H70: AI screening | I70: Selected Screening
A71: 46125 | B71: 0.66666667 | C71: Nareshkannan N | D71: Prodian(L-1) | E71: Thanishka | F71: Sumeet | G71: Done | H71: Done | I71: Rejected L1
A72: 46125 | B72: 0.66666667 | C72: Mohammed Rehan Y | D72: Zecdata(AI Screening) | E72: Veeru | F72: Ariprasath | G72: Done | H72: AI screening | I72: Selected Screening
A73: 46126 | B73: F2F | C73: Pooja Patil | D73: Geeky Ants(L-3 F2F) | E73: Ruchitha | F73: Sumeet | G73: Done | H73: Done | I73: Selected F2F
A74: 46126 | B74: 0.5 | C74: Mohammed Rehan Y | D74: Hurix(Screening) | E74: Veeru | F74: Sameer | G74: Done | H74: Done | I74: Waiting for Update
A75: 46126 | B75: 0.52083333 | C75: Nareshkannan N | D75: Expand My Business(Screening) | E75: Phoenix | F75: Sumeet | G75: Done | H75: Done
A76: 46126 | B76: 0.52083333 | C76: Soumyadeep Das | D76: Expand My Business(Screening) | E76: Phoenix | F76: Sumeet | G76: Done | H76: Done
A77: 46126 | B77: 0.54166667 | C77: Swati G Madiwalar | D77: Geeky Ants(L-1) | E77: Ruchitha | F77: Sumeet | G77: Done | H77: Done | I77: Selected L1
A78: 46126 | B78: 0.58333333 | C78: Tapas Kumar Paul | D78: Geeky Ants(L-1) | E78: Ruchitha | F78: Sumeet | G78: Done | H78: Done | I78: Rejected L1
A79: 46126 | B79: 0.61458333 | C79: Sunil K | D79: Hurix(Screening) | E79: Veeru | F79: Sameer | G79: Done | H79: Done
A80: 46126 | B80: 0.625 | C80: Manoj T | D80: Geeky Ants(L-1) | E80: Ruchitha | F80: Sumeet | G80: Done | H80: Done | I80: Selected L1
A81: 46126 | B81: 0.66666667 | C81: Arpitha N | D81: Geeky Ants(L-1) | E81: Ruchitha | F81: Sumeet | G81: Done | H81: Done | I81: Selected L1
A82: 46126 | B82: 0.66666667 | C82: Srinivas G | D82: Medimpact(L-2) | E82: Ruchitha | F82: Ariprasath | G82: Done | H82: Done | I82: Selected L2
A83: 46126 | B83: 0.67361111 | C83: Mohammed Rehan Y | D83: Zecdata(L-2) | E83: Ruchitha | F83: Sumeet | G83: Done | H83: AI screening
A84: 46126 | B84: 0.67361111 | C84: Ganesh S | D84: Zecdata(L-2) | E84: Ruchitha | F84: Sumeet | G84: Done | H84: AI screening
A85: 46127 | B85: 0.5 | C85: Arpitha N | D85: Zecdata(Screening) | E85: Ruchitha | F85: Sumeet | G85: Done | H85: Done | I85: Selected Screening
A86: 46127 | B86: 0.5 | C86: Bhaswat Abhishek Shandilya | D86: Zecdata(Screening) | E86: Ruchitha | F86: Sumeet | G86: Done | H86: Done | I86: Selected Screening
A87: 46127 | B87: 0.5625 | C87: Vaishnavi Hokrana | D87: Medimpact(L-1) | E87: Veeru | F87: Ariprasath | G87: Done | H87: Done | I87: Rejected L1
A88: 46127 | B88: 0.625 | C88: Niranjan Balaji N | D88: Prodian(L-1) | E88: Thanishka | F88: Sumeet | G88: Rescheduled | H88: Rescheduled | I88: Rescheduled
A89: 46127 | B89: 0.64583333 | C89: Kunda Venkata Krishnaveni | D89: Medimpact(L-1) | E89: Veeru | F89: Ariprasath | G89: Done | H89: Done | I89: Rejected L1
A90: 46127 | B90: 0.72916667 | C90: Sukesh Kumar | D90: Expand My Business(L-1) | E90: Phoenix | F90: Sumeet | G90: Done | H90: Done | I90: Rejected L1
A91: 46128 | B91: 0.375 | C91: Suramya S | D91: Zecdata(L-1) | E91: Ruchitha | F91: Sumeet | G91: Done | H91: Done | I91: Selected L1
A92: 46128 | B92: 0.5625 | C92: Saransh Vijay | D92: Geeky Ants(L-1) | E92: Ruchitha | F92: Sumeet | G92: Done | H92: Done | I92: Rejected L1
A93: 46128 | B93: 0.58333333 | C93: Shajeer Ali | D93: Expand My Business(L-1) | E93: Phoenix | F93: Sameer | G93: Done | H93: Done
A94: 46128 | B94: F2F | C94: Srinivas G | D94: Medimpact(L-3 F2F) | E94: Phoenix | F94: Sameer | G94: Done | H94: Done | I94: Selected L3
A95: 46128 | B95: 0.64583333 | C95: Mohammed Rehan Y | D95: Expand My Business(L-1) | E95: Phoenix | F95: Sameer | G95: Done
A96: 46128 | B96: 0.64583333 | C96: Samarpan Sarkar | D96: Xebia(L-1) | E96: Sadiya | F96: Sameer | G96: Done | H96: Done | I96: Rejected L1
A97: 46128 | B97: 0.69791667 | C97: Arpitha N | D97: Zecdata(Client Screening) | E97: Ruchitha | F97: Sumeet | G97: Done | H97: Done
A98: 46128 | B98: 0.71875 | C98: Bhaswat Abhishek Shandilya | D98: Zecdata(Client Screening) | E98: Ruchitha | F98: Sumeet | G98: Done | H98: Done
A99: 46128 | B99: 0.75 | C99: Adoni Meenakshi Naidu | D99: Xebia(L-1) | E99: Sadiya | F99: Sumeet | G99: Done | H99: Done | I99: Rejected L1
A100: 46128 | B100: 0.75 | C100: Bushra Sultana | D100: Xebia(L-1) | E100: Sadiya | F100: Manjunath | G100: Rescheduled | H100: Rescheduled | I100: Rescheduled
A101: 46128 | B101: 0.75 | C101: Ajith RG | D101: Geeky Ants(L-1) | E101: Ruchitha | F101: Sumeet | G101: Done | H101: Done | I101: Rejected L1
A102: 46129 | B102: 0.375 | C102: Rohith Raj | D102: Zecdata(L-1) | E102: Ruchitha | F102: Sumeet | G102: Done | H102: Done | I102: Not Applicable
A103: 46129 | B103: 0.45833333 | C103: Sunil K | D103: Kognivera(L-1) | E103: Ruchitha | F103: Sameer | G103: Done | H103: Done | I103: Selected L1
A104: 46129 | B104: 0.5 | C104: Suramya S | D104: Zecdata(Client Prep Call) | E104: Ruchitha | F104: Sumeet | G104: Done | H104: Prep Call | I104: Prep Call
A105: 46129 | B105: 0.75 | C105: Bushra Sultana | D105: Xebia(L-1) | E105: Sadiya | F105: Manjunath | G105: Done | H105: Done | I105: Selected L1
A106: 46132 | B106: 0.625 | C106: Srinivas G | D106: Medimpact(L-4 HR) | E106: Veeru | F106: Sumeet | G106: Done | H106: Done | I106: Selected L4 HR
A107: 46132 | B107: 0.625 | C107: Rohan Paul | D107: Rebit(L-1) | E107: Thanishka | F107: Sumeet | G107: Done | H107: Done | I107: On Hold
A108: 46132 | B108: 0.63541667 | C108: Pavan Kumar Buduru | D108: Rebit(L-1) | E108: Thanishka | F108: Sumeet | G108: Done | H108: Done | I108: Rejected L1
A109: 46132 | B109: 0.65625 | C109: Adoni Meenakshi Naidu | D109: Rebit(L-1) | E109: Thanishka | F109: Sumeet | G109: Done | H109: Done | I109: Rejected L1
A110: 46132 | B110: 0.70833333 | C110: Aditya Vijay Barathe | D110: Rebit(L-3) | E110: Thanishka | F110: Manjunath | G110: Done | H110: Done | I110: Selected L3
... A115: 46132 | B115: 0.72916667 | C115: Nareshkannan N | D115: Medimpact(Online Test) | E115: Ruchitha | F115: Manjunath | G115: Done | H115: Online Test | I115: Selected Online Test
A116: 46133 | B116: 0.5 | C116: Bushra Sultana | D116: Deservely(L-1) | E116: Ruchitha | F116: Manjunath | G116: Done | H116: Done
A117: 46133 | B117: 0.625 | C117: Sunil K | D117: Kognivera(L-2) | E117: Ruchitha | F117: Sameer | G117: Done | H117: Done | I117: Rejected L2
A118: 46133 | B118: 0.66666667 | C118: Ajith RG | D118: Expand My Business(L-1) | E118: Phoenix | F118: Sumeet | G118: Done | H118: Done | I118: Rejected L1
A119: 46133 | B119: 0.66666667 | C119: Arpitha N | D119: Medimpact(L-1) | E119: Veeru | F119: Sumeet | G119: Done | H119: Done | I119: Selected L1
A120: 46133 | B120: 0.70833333 | C120: Deepak Kumar | D120: Rebit(L-2) | E120: Thanishka | F120: Sumeet | G120: Done | H120: Done
A121: 46133 | B121: 0.75 | C121: Bushra Sultana | D121: Xebia(L-2) | E121: Sadiya | F121: Manjunath | G121: Done | H121: Done
A122: 46133 | B122: 0.75 | C122: Bhaswat Abhishek Shandilya | D122: Xebia(L-1) | E122: Sadiya | F122: Sumeet | G122: Rescheduled | H122: Rescheduled | I122: Rescheduled
A123: 46134 | B123: 0.45833333 | C123: Sukesh Kumar | D123: Geeky Ants(L-1) | E123: Ruchitha | F123: Sumeet | G123: Done | H123: Done
A124: 46134 | B124: 0.47916667 | C124: Manoj T | D124: Prodian(L-1) | E124: Thanishka | F124: Shreya | G124: Done | H124: Done | I124: Rejected L1
A125: 46134 | B125: 0.5 | C125: Lakku Jaya Prakash Reddy | D125: Geeky Ants(L-1) | E125: Ruchitha | F125: Sumeet | G125: Done | H125: Done
A126: 46134 | B126: 0.5625 | C126: Adoni Meenakshi Naidu | D126: Medimpact(L-1) | E126: Veeru | F126: Sumeet | G126: Done | H126: Done | I126: Selected L1
A127: 46134 | B127: 0.625 | C127: Arpitha N | D127: Medimpact(L-2) | E127: Veeru | F127: Sumeet | G127: Done | H127: Done | I127: Rejected L2
A128: 46134 | B128: 0.64583333 | C128: Deepak Kumar | D128: Medimpact(L-1) | E128: Veeru | F128: Sumeet | G128: Done | H128: Done | I128: Rejected L1
A129: 46134 | B129: 0.64583333 | C129: Nareshkannan N | D129: Medimpact(L-1) | E129: Veeru | F129: Sumeet | G129: Done
A130: 46134 | B130: 0.75 | C130: Bhaswat Abhishek Shandilya | D130: Xebia(L-1) | E130: Sadiya | F130: Sumeet | G130: Rescheduled
A131: 46135 | B131: 0.5 | C131: Bushra Sultana | D131: Xebia(L-3) | E131: Sadiya | F131: Sumeet | G131: Done | I131: Final Select
A132: 46135 | B132: 0.625 | C132: Adoni Meenakshi Naidu | D132: Medimpact(L-2) | E132: Veeru | F132: Sumeet | G132: Done | I132: Selected L2
A133: 46135 | B133: 0.625 | C133: Soumyadeep Das | D133: Medimpact(Online Test) | E133: Veeru | F133: Sumeet | G133: Done
A134: 46135 | B134: 0.625 | C134: Suramya S | D134: Medimpact(Online Test) | E134: Veeru | F134: Sumeet | G134: Done
A135: 46135 | B135: 0.625 | C135: Sthita Prajna Satapathy | D135: Medimpact(Online Test) | E135: Veeru | F135: Sumeet | G135: Done

Sheet Market Intv Data
A1: Candidate Name | B1: Client | C1: Skills | D1: Date | E1: Time | F1: Recruiter | G1: Status
A2: Shantanu Hingane | B2: AhanaIT | C2: Data Engineering Support | D2: 46114 | E2: 0.666667 | F2: Archana | G2: L1 Reject
A3: A P Bhuvanesh | B3: ARM | C3: SAP O2C | D3: 46114 | E3: 0.708333 | F3: Roshini | G3: L2 Reject
A4: Abhishek Dwivedi | B4: GreenTube | C4: Playwright Automation | D4: 46114 | E4: 0.708333 | F4: Roshini | G4: L1 Select , Client Hold
A5: Sathish | B5: Vyvpar | C5: Android Developer | D5: 46115 | E5: 0.541667 | F5: Apoorva | G5: L1 Completed, no updates from client
A6: Piyush Kesarwani | B6: Byteridge | C6: .Net | D6: 46120 | E6: 0.541667 | F6: Archana | G6: L1 Reject
A7: Sanket Bandal | B7: AhanaIT | C7: Data Engineering Support | D7: 46120 | E7: 0.875 | F7: Archana | G7: Final select-Joinee no show
A8: Abhishek Shivanand Biradar | B8: ARM | C8: SAP SD | D8: 46120 | E8: 0.625 | F8: Roshini | G8: L2 Reject
A9: Swapnil Zende | B9: XPO | C9: Python | D9: 46122 | E9: 0.666667 | F9: Archana | G9: L1 Reject
A10: Sunitha | B10: Saksoft | C10: .Net | D10: 46122 | E10: 0.541667 | F10: Apoorva | G10: L1 Reject
A11: Sushant | B11: Saksoft | C11: .Net | D11: 46122 | E11: 0.625 | F11: Apoorva | G11: L1 Reject
A12: Muhil Anirudh | B12: Byteridge | C12: Backend Developer | D12: 46122 | E12: 0.5 | F12: Reshma | G12: L1 Reject
A13: Mahalakshmi | B13: Byteridge | C13: Backend Developer | D13: 46122 | E13: 0.708333 | F13: Apoorva | G13: L1 Reject
... A33: Vidya M | B33: Coverfox | C33: Android Developer | D33: 46135 | E33: 0.625 | F33: Apoorva | G33: L1 Completed Feedback pending
A34: Sairam | B34: NPCI | C34: SRE | D34: 46135 | E34: 1!:30 AM | F34: Archana | G34: L1 Completed
A35: Tejas Kachave | B35: XPO | C35: Python | D35: 46135 | E35: 0.770833 | F35: Archana | G35: L1 Scheduled
A36: Dhanushya | B36: Coverfox | C36: Android Developer | D36: 46135 | E36: 0.729167 | F36: Apoorva | G36: L1 Completed Feedback pending

Sheet Instructions
A1: BD Operations Dashboard — How to use
A3: Purpose | B3: Standalone analytics dashboard derived from BD_DAR.xlsx. Gives executive view + 6 deep-dive tabs.
A5: Tabs in this workbook
A6: 1. Executive Summary | B6: TOP-LINE KPIs + 'Story in 3 numbers' + 8 takeaways. Open this first in CEO meetings.
A7: 2. BD Funnel | B7: Submission → Profile Shared → Interview → Shortlisted → Selected → Onboarded with conversion at each stage.
A8: 3. Account Scorecard | B8: Per-client breakdown: submissions, onboards, reject rate, onboard rate. Sorted by total submissions.
A9: 4. Skill Gap | B9: Demand from BD vs Supply on bench. Flags HIRE recommendations for skills with no bench.
A10: 5. BD Performance | B10: Per-BD interview metrics (Veeru, Ruchitha etc) + per-Recruiter market metrics (Reshma, Apoorva etc).
A11: 6. Hard-to-Place | B11: Resources with most interviews who haven't placed. Includes their bench status & rating.
A12: 7. Bench vs Market | B12: Side-by-side sourcing comparison with conversion rates.
A13: 8-11. *_Data tabs | B13: Source data copied from BD_DAR. UPDATE THESE to refresh the dashboard.
A15: How to refresh data
A16: Step 1 | B16: Open BD_DAR.xlsx and the relevant source sheet (BD / Bench / Bench Interview / Market Interview).
A17: Step 2 | B17: Copy the data range (no headers, just the rows below row 1).
A18: Step 3 | B18: Paste into the corresponding *_Data tab here, starting at row 2. Overwrite existing data.
A19: Step 4 | B19: All dashboard tabs auto-update. Press F9 if calculations don't refresh immediately.
A20: Step 5 | B20: If row count grows beyond original, you may need to extend formula ranges (currently set to current row counts).
A22: Colour code
A23: Yellow | B23: Input / action cell — type here
A24: Light gray | B24: Auto-calculated — don't type
A25: Green | B25: Good (high onboard rate, asset bench, aligned skill, bench leads)
A26: Amber | B26: Watch (medium rating, gap warning)
A27: Red | B27: Bad (high reject rate, hire-needed skill, liability)
A28: Gold | B28: Section header / important callout
A30: Limitations
A31: Data freshness | B31: Dashboard reflects whatever is in *_Data tabs. Refresh weekly minimum.
A32: Skill matching | B32: Uses partial-text matching (e.g. 'Java' matches 'Java + SB' and 'Java/GoLang'). May overcount in edge cases.
A33: Account list | B33: Account Scorecard only shows accounts I pre-loaded. Add new ones in column A as they appear in BD.
A34: Data quality | B34: Some BD rows have inconsistent capitalisation ('Profile Rejected' vs 'profile rejected'). I count both, but cleaning the source improves accuracy.
